{
  "id": "fs%2Flustre-release~57192",
  "triplet_id": "fs%2Flustre-release~master~I7807263d71cd3fc8a9934cc4c4da8b497b845e6f",
  "project": "fs/lustre-release",
  "branch": "master",
  "hashtags": [],
  "change_id": "I7807263d71cd3fc8a9934cc4c4da8b497b845e6f",
  "subject": "LU-18497 gss: carry out creds prepare as user",
  "status": "MERGED",
  "created": "2024-11-28 12:08:42.000000000",
  "updated": "2024-12-16 08:19:38.000000000",
  "submitted": "2024-12-16 08:19:38.000000000",
  "submitter": {
    "_account_id": 112,
    "name": "Oleg Drokin",
    "email": "green@whamcloud.com",
    "username": "green"
  },
  "insertions": 69,
  "deletions": 118,
  "total_comment_count": 6,
  "unresolved_comment_count": 2,
  "has_review_started": true,
  "submission_id": "57192-1734337178134-915724bd",
  "meta_rev_id": "3912f81340ef081adc7e61b7082f095b0baa6968",
  "_number": 57192,
  "virtual_id_number": 57192,
  "owner": {
    "_account_id": 597,
    "name": "Sebastien Buisson",
    "email": "sbuisson@ddn.com",
    "username": "sbuisson"
  },
  "labels": {
    "Verified": {
      "all": [
        {
          "value": 0,
          "_account_id": 793,
          "name": "Aurelien Degremont",
          "email": "adegremont@nvidia.com",
          "username": "degremoa"
        },
        {
          "tag": "autogenerated:gerrit:merged",
          "value": 1,
          "date": "2024-12-16 08:19:38.000000000",
          "permitted_voting_range": {
            "min": 1,
            "max": 1
          },
          "_account_id": 683,
          "name": "jenkins",
          "email": "devops@whamcloud.com",
          "username": "jenkins",
          "tags": [
            "SERVICE_USER"
          ]
        },
        {
          "value": 0,
          "_account_id": 117,
          "name": "Andreas Dilger",
          "email": "adilger@thelustrecollective.com",
          "username": "adilger"
        },
        {
          "value": 0,
          "_account_id": 112,
          "name": "Oleg Drokin",
          "email": "green@whamcloud.com",
          "username": "green"
        },
        {
          "tag": "autogenerated:gerrit:merged",
          "value": 1,
          "date": "2024-12-16 08:19:38.000000000",
          "permitted_voting_range": {
            "min": 1,
            "max": 1
          },
          "_account_id": 147,
          "name": "Maloo",
          "email": "maloo@whamcloud.com",
          "username": "maloo",
          "tags": [
            "SERVICE_USER"
          ]
        }
      ],
      "values": {
        "-1": "Fails",
        " 0": "No score",
        "+1": "Verified"
      },
      "description": "",
      "default_value": 0
    },
    "Code-Review": {
      "all": [
        {
          "tag": "autogenerated:gerrit:merged",
          "value": 1,
          "date": "2024-12-16 08:19:38.000000000",
          "permitted_voting_range": {
            "min": 1,
            "max": 1
          },
          "_account_id": 793,
          "name": "Aurelien Degremont",
          "email": "adegremont@nvidia.com",
          "username": "degremoa"
        },
        {
          "value": 0,
          "_account_id": 683,
          "name": "jenkins",
          "email": "devops@whamcloud.com",
          "username": "jenkins",
          "tags": [
            "SERVICE_USER"
          ]
        },
        {
          "tag": "autogenerated:gerrit:merged",
          "value": 1,
          "date": "2024-12-16 08:19:38.000000000",
          "permitted_voting_range": {
            "min": 1,
            "max": 1
          },
          "_account_id": 117,
          "name": "Andreas Dilger",
          "email": "adilger@thelustrecollective.com",
          "username": "adilger"
        },
        {
          "tag": "autogenerated:gerrit:merged",
          "value": 2,
          "date": "2024-12-16 08:19:38.000000000",
          "permitted_voting_range": {
            "min": 2,
            "max": 2
          },
          "_account_id": 112,
          "name": "Oleg Drokin",
          "email": "green@whamcloud.com",
          "username": "green"
        },
        {
          "value": 0,
          "_account_id": 147,
          "name": "Maloo",
          "email": "maloo@whamcloud.com",
          "username": "maloo",
          "tags": [
            "SERVICE_USER"
          ]
        }
      ],
      "values": {
        "-2": "Do not submit",
        "-1": "I would prefer that you didn't submit this",
        " 0": "No score",
        "+1": "Looks good to me, but someone else must approve",
        "+2": "Looks good to me, approved"
      },
      "description": "",
      "default_value": 0
    }
  },
  "removable_reviewers": [
    {
      "_account_id": 597,
      "name": "Sebastien Buisson",
      "email": "sbuisson@ddn.com",
      "username": "sbuisson"
    },
    {
      "_account_id": 689,
      "name": "Jeremy Filizetti",
      "email": "jeremy.filizetti@gmail.com",
      "username": "jfilizetti"
    }
  ],
  "reviewers": {
    "REVIEWER": [
      {
        "_account_id": 112,
        "name": "Oleg Drokin",
        "email": "green@whamcloud.com",
        "username": "green"
      },
      {
        "_account_id": 117,
        "name": "Andreas Dilger",
        "email": "adilger@thelustrecollective.com",
        "username": "adilger"
      },
      {
        "_account_id": 147,
        "name": "Maloo",
        "email": "maloo@whamcloud.com",
        "username": "maloo",
        "tags": [
          "SERVICE_USER"
        ]
      },
      {
        "_account_id": 597,
        "name": "Sebastien Buisson",
        "email": "sbuisson@ddn.com",
        "username": "sbuisson"
      },
      {
        "_account_id": 683,
        "name": "jenkins",
        "email": "devops@whamcloud.com",
        "username": "jenkins",
        "tags": [
          "SERVICE_USER"
        ]
      },
      {
        "_account_id": 689,
        "name": "Jeremy Filizetti",
        "email": "jeremy.filizetti@gmail.com",
        "username": "jfilizetti"
      },
      {
        "_account_id": 793,
        "name": "Aurelien Degremont",
        "email": "adegremont@nvidia.com",
        "username": "degremoa"
      }
    ],
    "CC": [
      {
        "_account_id": 377,
        "name": "wc-checkpatch",
        "username": "hpdd-checkpatch",
        "tags": [
          "SERVICE_USER"
        ]
      },
      {
        "_account_id": 403,
        "name": "Autotest",
        "email": "autotest@whamcloud.com",
        "username": "autotest",
        "tags": [
          "SERVICE_USER"
        ]
      },
      {
        "_account_id": 799,
        "name": "Lustre Gerrit Janitor",
        "email": "lgerrit@linuxhacker.ru",
        "username": "lgerritjanitor",
        "tags": [
          "SERVICE_USER"
        ]
      }
    ]
  },
  "pending_reviewers": {},
  "messages": [
    {
      "id": "3b7fd40d75ac16b7efab2c78a0dbf7893f2ff86c",
      "tag": "autogenerated:gerrit:newPatchSet",
      "author": {
        "_account_id": 597,
        "name": "Sebastien Buisson",
        "email": "sbuisson@ddn.com",
        "username": "sbuisson"
      },
      "date": "2024-11-28 12:08:42.000000000",
      "message": "Uploaded patch set 1.",
      "accounts_in_message": [],
      "_revision_number": 1
    },
    {
      "id": "71a9c2e52f9d3206e0ffadf67ccfe567f0ca8a94",
      "author": {
        "_account_id": 377,
        "name": "wc-checkpatch",
        "username": "hpdd-checkpatch",
        "tags": [
          "SERVICE_USER"
        ]
      },
      "date": "2024-11-28 12:10:40.000000000",
      "message": "Patch Set 1:\n\nLooks good to me.",
      "accounts_in_message": [],
      "_revision_number": 1
    },
    {
      "id": "63c15478dce19e777afd6545e1be7df600c4aca3",
      "author": {
        "_account_id": 799,
        "name": "Lustre Gerrit Janitor",
        "email": "lgerrit@linuxhacker.ru",
        "username": "lgerritjanitor",
        "tags": [
          "SERVICE_USER"
        ]
      },
      "date": "2024-11-28 12:11:48.000000000",
      "message": "Patch Set 1:\n\n(1 comment)\n\nBuilds for x86_64 centos7,rhel8.5 successful\nJob output URL: https://testing.whamcloud.com/gerrit-janitor/47422/results.html\n\n Commencing initial testing: runtests@ldiskfs+DNE runtests-ssk@ldiskfs+SharedKey runtests@zfs",
      "accounts_in_message": [],
      "_revision_number": 1
    },
    {
      "id": "4e2827a54dc1b1afa52a4b2c96fab547a2c93851",
      "author": {
        "_account_id": 799,
        "name": "Lustre Gerrit Janitor",
        "email": "lgerrit@linuxhacker.ru",
        "username": "lgerritjanitor",
        "tags": [
          "SERVICE_USER"
        ]
      },
      "date": "2024-11-28 12:25:16.000000000",
      "message": "Patch Set 1:\n\nInitial testing succeeded.\n\nSucceeded:\n- runtests@ldiskfs+DNE runtests-ssk@ldiskfs+SharedKey runtests@zfs \n\n(centos7)All results and logs: https://testing.whamcloud.com/gerrit-janitor/47422/results.html\nCommencing standard testing: \n- conf-sanity1@ldiskfs+DNE conf-sanity2@ldiskfs+DNE conf-sanity3@ldiskfs+DNE conf-sanity-slow@ldiskfs+DNE conf-sanity-slow-106@ldiskfs+DNE conf-sanity1@zfs conf-sanity2@zfs conf-sanity3@zfs conf-sanity-slow@zfs conf-sanity-slow-106@zfs insanity@ldiskfs+DNE insanity@zfs lnet-selftest@zfs lustre-rsync-test@ldiskfs+DNE lustre-rsync-test@zfs ost-pools@ldiskfs+DNE ost-pools@zfs pjdfstest@ldiskfs+DNE pjdfstest@zfs racer@ldiskfs+DNE racer@zfs recovery-small@ldiskfs+DNE recovery-small@zfs replay-dual@ldiskfs+DNE replay-dual@zfs replay-ost-single@ldiskfs+DNE replay-ost-single@zfs replay-single@ldiskfs+DNE replay-single@zfs replay-vbr@ldiskfs+DNE replay-vbr@zfs sanity1@ldiskfs+DNE sanity2@ldiskfs+DNE sanity-slow@ldiskfs+DNE sanity1@zfs sanity2@zfs sanity-slow@zfs sanity-benchmark@ldiskfs+DNE sanity-benchmark@zfs sanity-dom@ldiskfs+DNE sanity-dom@zfs sanity-flr@ldiskfs+DNE sanity-flr@zfs sanity-hsm@ldiskfs+DNE sanity-hsm@zfs sanity-lfsck@ldiskfs+DNE sanity-lfsck@zfs sanity-lnet@zfs sanity-pcc@ldiskfs+DNE sanity-pcc@zfs sanity-pfl@ldiskfs+DNE sanity-pfl@zfs sanity-quota@ldiskfs+DNE sanity-quota@zfs sanity-scrub@ldiskfs+DNE sanity-scrub@zfs sanity-sec@ldiskfs+DNE sanity-sec@zfs sanityn@ldiskfs+DNE sanityn@zfs",
      "accounts_in_message": [],
      "_revision_number": 1
    },
    {
      "id": "b4e2dfa3fc7f2eafa7bf0078e5095ba58b85bb5a",
      "author": {
        "_account_id": 683,
        "name": "jenkins",
        "email": "devops@whamcloud.com",
        "username": "jenkins",
        "tags": [
          "SERVICE_USER"
        ]
      },
      "date": "2024-11-28 13:29:35.000000000",
      "message": "Patch Set 1: Verified+1\n\nBuild Successful \n\nhttps://build.whamcloud.com/job/lustre-reviews/109224/ : SUCCESS",
      "accounts_in_message": [],
      "_revision_number": 1
    },
    {
      "id": "1699befc83a4f6fd3c79d240e65673b4ebf40a96",
      "author": {
        "_account_id": 147,
        "name": "Maloo",
        "email": "maloo@whamcloud.com",
        "username": "maloo",
        "tags": [
          "SERVICE_USER"
        ]
      },
      "date": "2024-11-28 13:31:57.000000000",
      "message": "Patch Set 1:\n\nThe following sessions will be run for build 109224 patch 1\n\nEnforced:\n- review-ldiskfs-dne on el8.10-x86_64/ldiskfs servers and clients\n- review-ldiskfs-dne on el9.3-x86_64/ldiskfs servers and clients\n- review-dne-selinux-ssk-part-1 on el8.10-x86_64/ldiskfs servers and clients\n- review-dne-selinux-ssk-part-2 on el8.10-x86_64/ldiskfs servers and clients\n- custom on el8.10-x86_64/ldiskfs servers and clients\n\nOptional:\n- review-ldiskfs-dne-arm on el8.10-x86_64/ldiskfs servers and el9.3-aarch64/ldiskfs clients\n\nMaloo Test Queue: https://testing.whamcloud.com/test_queue?jobs=lustre-reviews&builds=109224&commit=Apply+Filter\nMaloo Results: https://testing.whamcloud.com/test_sessions/related?jobs=lustre-reviews&builds=109224#redirect",
      "accounts_in_message": [],
      "_revision_number": 1
    },
    {
      "id": "51255ec91edc593ab071ed6e662b62da9c837751",
      "author": {
        "_account_id": 147,
        "name": "Maloo",
        "email": "maloo@whamcloud.com",
        "username": "maloo",
        "tags": [
          "SERVICE_USER"
        ]
      },
      "date": "2024-11-28 15:23:27.000000000",
      "message": "Patch Set 1:\n\nFailed enforced test custom-1003 on RHEL 8.10 / x86_64 uploaded by Onyx Autotest 2 from onyx-49vm4: https://testing.whamcloud.com/test_sessions/53f63687-6014-4885-ac25-10ac75cfe619 ran 3 tests.  1 tests failed: sanity-krb5.",
      "accounts_in_message": [],
      "_revision_number": 1
    },
    {
      "id": "2b7a693e864cdbf148e830f092d399895fe508b3",
      "author": {
        "_account_id": 403,
        "name": "Autotest",
        "email": "autotest@whamcloud.com",
        "username": "autotest",
        "tags": [
          "SERVICE_USER"
        ]
      },
      "date": "2024-11-28 15:41:26.000000000",
      "message": "Patch Set 1:\n\nTrevis Autotest 2 retesting enforced custom session on el8.10-x86_64/ldiskfs servers and clients for build 109224 patch 1. Requested by S Buisson because of LU-18497.\nThe following test parameters were specified: kerberos=true testlist=sanity-krb5.",
      "accounts_in_message": [],
      "_revision_number": 1
    },
    {
      "id": "7425ee3139dcd49fe8cc53d19b229d773957f364",
      "author": {
        "_account_id": 799,
        "name": "Lustre Gerrit Janitor",
        "email": "lgerrit@linuxhacker.ru",
        "username": "lgerritjanitor",
        "tags": [
          "SERVICE_USER"
        ]
      },
      "date": "2024-11-28 16:04:02.000000000",
      "message": "Patch Set 1:\n\nEven though \"Test-Parameters: trivial\" was detected, this deeply suspicious bot still run some testing\n\nTesting has completed with errors!\nIMPORTANT: these tests appear to be new failures unique to this patch\n- conf-sanity2@ldiskfs+DNE:test_50i(Seen in reviews: 56607 56527 56489 56455 56420 56407 56058 55801 55695 55642 55571 55475 55449 55361 54735 54606 54548 54314 54169 53896 53758 53757 53625 53377 53310 52636 52075 50099 47226 47160 47150 46775 46763 46282 45890 45882 45353 45099 43581 43290 41994 38845 36469 36202)\n\n\n> conf-sanity2@ldiskfs+DNE Failure(5509s)\n- 50i(create files failed) \n> racer@ldiskfs+DNE Timeout(2007s)\n> racer@zfs Timeout(2011s)\n\nSucceeded:\n- conf-sanity1@ldiskfs+DNE conf-sanity3@ldiskfs+DNE conf-sanity-slow@ldiskfs+DNE conf-sanity-slow-106@ldiskfs+DNE conf-sanity1@zfs conf-sanity2@zfs conf-sanity3@zfs conf-sanity-slow@zfs conf-sanity-slow-106@zfs insanity@ldiskfs+DNE insanity@zfs lnet-selftest@zfs lustre-rsync-test@ldiskfs+DNE lustre-rsync-test@zfs ost-pools@ldiskfs+DNE ost-pools@zfs pjdfstest@ldiskfs+DNE pjdfstest@zfs recovery-small@ldiskfs+DNE recovery-small@zfs replay-dual@ldiskfs+DNE replay-dual@zfs replay-ost-single@ldiskfs+DNE replay-ost-single@zfs replay-single@ldiskfs+DNE replay-single@zfs replay-vbr@ldiskfs+DNE replay-vbr@zfs sanity1@ldiskfs+DNE sanity2@ldiskfs+DNE sanity-slow@ldiskfs+DNE sanity1@zfs sanity2@zfs sanity-slow@zfs sanity-benchmark@ldiskfs+DNE sanity-benchmark@zfs sanity-dom@ldiskfs+DNE sanity-dom@zfs sanity-flr@ldiskfs+DNE sanity-flr@zfs sanity-hsm@ldiskfs+DNE sanity-hsm@zfs sanity-lfsck@ldiskfs+DNE sanity-lfsck@zfs sanity-lnet@zfs sanity-pcc@ldiskfs+DNE sanity-pcc@zfs sanity-pfl@ldiskfs+DNE sanity-pfl@zfs sanity-quota@ldiskfs+DNE sanity-quota@zfs sanity-scrub@ldiskfs+DNE sanity-scrub@zfs sanity-sec@ldiskfs+DNE sanity-sec@zfs sanityn@ldiskfs+DNE sanityn@zfs \n\n(centos7)All results and logs: https://testing.whamcloud.com/gerrit-janitor/47422/results.html",
      "accounts_in_message": [],
      "_revision_number": 1
    },
    {
      "id": "c3842d664291e1771c3db88b69bb686a00f104eb",
      "author": {
        "_account_id": 793,
        "name": "Aurelien Degremont",
        "email": "adegremont@nvidia.com",
        "username": "degremoa"
      },
      "date": "2024-11-28 16:26:56.000000000",
      "message": "Patch Set 1: Code-Review+1",
      "accounts_in_message": [],
      "_revision_number": 1
    },
    {
      "id": "f10d397f83ecbb61df65026f6c41429b6bd88e81",
      "author": {
        "_account_id": 147,
        "name": "Maloo",
        "email": "maloo@whamcloud.com",
        "username": "maloo",
        "tags": [
          "SERVICE_USER"
        ]
      },
      "date": "2024-11-28 16:54:45.000000000",
      "message": "Patch Set 1:\n\nFailed enforced test custom-1003 on RHEL 8.10 / x86_64 uploaded by Trevis Autotest 2 from trevis-31vm1: https://testing.whamcloud.com/test_sessions/01946992-25ab-4c51-9d2b-d008c677fd16 ran 3 tests.  1 tests failed: sanity-krb5.",
      "accounts_in_message": [],
      "_revision_number": 1
    },
    {
      "id": "05b16cc441c2234d37b7b5491923e54822b4bdcc",
      "author": {
        "_account_id": 597,
        "name": "Sebastien Buisson",
        "email": "sbuisson@ddn.com",
        "username": "sbuisson"
      },
      "date": "2024-11-28 17:02:08.000000000",
      "message": "Patch Set 1:\n\n> Patch Set 1:\n> \n> Failed enforced test custom-1003 on RHEL 8.10 / x86_64 uploaded by Trevis Autotest 2 from trevis-31vm1: https://testing.whamcloud.com/test_sessions/01946992-25ab-4c51-9d2b-d008c677fd16 ran 3 tests.  1 tests failed: sanity-krb5.\n\nI need to investigate why sanity-krb5 test_5 and test_10 are failing with this patch.",
      "accounts_in_message": [],
      "_revision_number": 1
    },
    {
      "id": "d90521eedce82c21544238533b5f9642b0c64637",
      "author": {
        "_account_id": 117,
        "name": "Andreas Dilger",
        "email": "adilger@thelustrecollective.com",
        "username": "adilger"
      },
      "date": "2024-11-28 18:07:33.000000000",
      "message": "Patch Set 1: Code-Review+1\n\n(1 comment)",
      "accounts_in_message": [],
      "_revision_number": 1
    },
    {
      "id": "352ca31ff644a53abf0c784f679156825a2967f6",
      "author": {
        "_account_id": 147,
        "name": "Maloo",
        "email": "maloo@whamcloud.com",
        "username": "maloo",
        "tags": [
          "SERVICE_USER"
        ]
      },
      "date": "2024-11-28 20:18:56.000000000",
      "message": "Patch Set 1: Verified-1\n\nFailed enforced test review-dne-selinux-ssk-part-1 on RHEL 8.10 / x86_64 uploaded by Onyx Autotest 2 from onyx-96vm4: https://testing.whamcloud.com/test_sessions/77e61fe5-2f46-44fc-9407-e0c078dc238c ran 3 tests.  1 tests failed: sanity.",
      "accounts_in_message": [],
      "_revision_number": 1
    },
    {
      "id": "bf56ee16a890f0fedf12db222095953362eacf6f",
      "author": {
        "_account_id": 403,
        "name": "Autotest",
        "email": "autotest@whamcloud.com",
        "username": "autotest",
        "tags": [
          "SERVICE_USER"
        ]
      },
      "date": "2024-11-29 18:24:38.000000000",
      "message": "Patch Set 1:\n\nTrevis Autotest 2 retesting enforced review-dne-selinux-ssk-part-1 session on el8.10-x86_64/ldiskfs servers and clients for build 109224 patch 1. Requested by Peter Jones because of test_51d.\nThe following test parameters were specified: testgroup=review-dne-selinux-ssk-part-1.",
      "accounts_in_message": [],
      "_revision_number": 1
    },
    {
      "id": "bb2471c42cbd5e9045292846815b84c44df3ffbc",
      "author": {
        "_account_id": 147,
        "name": "Maloo",
        "email": "maloo@whamcloud.com",
        "username": "maloo",
        "tags": [
          "SERVICE_USER"
        ]
      },
      "date": "2024-11-29 23:20:41.000000000",
      "message": "Patch Set 1:\n\nPassed enforced test review-dne-selinux-ssk-part-1 on RHEL 8.10 / x86_64 uploaded by Trevis Autotest 2 from trevis-101vm1: https://testing.whamcloud.com/test_sessions/0c095ed5-e086-4ac5-838d-07df24538e18 ran 3 tests.",
      "accounts_in_message": [],
      "_revision_number": 1
    },
    {
      "id": "40d650ee3f2ad3bc1ad150b55ce1d094abfbab27",
      "tag": "autogenerated:gerrit:newPatchSet",
      "author": {
        "_account_id": 597,
        "name": "Sebastien Buisson",
        "email": "sbuisson@ddn.com",
        "username": "sbuisson"
      },
      "date": "2024-12-03 16:21:54.000000000",
      "message": "Uploaded patch set 2.",
      "accounts_in_message": [],
      "_revision_number": 2
    },
    {
      "id": "ccf2697984ecc7801c29ca0b85af9b68347736ea",
      "author": {
        "_account_id": 377,
        "name": "wc-checkpatch",
        "username": "hpdd-checkpatch",
        "tags": [
          "SERVICE_USER"
        ]
      },
      "date": "2024-12-03 16:22:59.000000000",
      "message": "Patch Set 2:\n\nLooks good to me.",
      "accounts_in_message": [],
      "_revision_number": 2
    },
    {
      "id": "6ef55f3b272c33379669c8c4e61aae073fdfaa9a",
      "author": {
        "_account_id": 799,
        "name": "Lustre Gerrit Janitor",
        "email": "lgerrit@linuxhacker.ru",
        "username": "lgerritjanitor",
        "tags": [
          "SERVICE_USER"
        ]
      },
      "date": "2024-12-03 16:24:28.000000000",
      "message": "Patch Set 2:\n\n(1 comment)\n\nBuilds for x86_64 centos7,rhel8.5 successful\nJob output URL: https://testing.whamcloud.com/gerrit-janitor/47555/results.html\n\n Commencing initial testing: runtests@ldiskfs+DNE runtests-ssk@ldiskfs+SharedKey runtests@zfs",
      "accounts_in_message": [],
      "_revision_number": 2
    },
    {
      "id": "6c54c71f7632982620cf785cd42bb0df6e15f925",
      "author": {
        "_account_id": 799,
        "name": "Lustre Gerrit Janitor",
        "email": "lgerrit@linuxhacker.ru",
        "username": "lgerritjanitor",
        "tags": [
          "SERVICE_USER"
        ]
      },
      "date": "2024-12-03 16:34:15.000000000",
      "message": "Patch Set 2:\n\nInitial testing succeeded.\n\nSucceeded:\n- runtests@ldiskfs+DNE runtests-ssk@ldiskfs+SharedKey runtests@zfs \n\n(centos7)All results and logs: https://testing.whamcloud.com/gerrit-janitor/47555/results.html\nCommencing standard testing: \n- conf-sanity1@ldiskfs+DNE conf-sanity2@ldiskfs+DNE conf-sanity3@ldiskfs+DNE conf-sanity-slow@ldiskfs+DNE conf-sanity-slow-106@ldiskfs+DNE conf-sanity1@zfs conf-sanity2@zfs conf-sanity3@zfs conf-sanity-slow@zfs conf-sanity-slow-106@zfs insanity@ldiskfs+DNE insanity@zfs lnet-selftest@zfs lustre-rsync-test@ldiskfs+DNE lustre-rsync-test@zfs ost-pools@ldiskfs+DNE ost-pools@zfs pjdfstest@ldiskfs+DNE pjdfstest@zfs racer@ldiskfs+DNE racer@zfs recovery-small@ldiskfs+DNE recovery-small@zfs replay-dual@ldiskfs+DNE replay-dual@zfs replay-ost-single@ldiskfs+DNE replay-ost-single@zfs replay-single@ldiskfs+DNE replay-single@zfs replay-vbr@ldiskfs+DNE replay-vbr@zfs sanity1@ldiskfs+DNE sanity2@ldiskfs+DNE sanity-slow@ldiskfs+DNE sanity1@zfs sanity2@zfs sanity-slow@zfs sanity-benchmark@ldiskfs+DNE sanity-benchmark@zfs sanity-dom@ldiskfs+DNE sanity-dom@zfs sanity-flr@ldiskfs+DNE sanity-flr@zfs sanity-hsm@ldiskfs+DNE sanity-hsm@zfs sanity-lfsck@ldiskfs+DNE sanity-lfsck@zfs sanity-lnet@zfs sanity-pcc@ldiskfs+DNE sanity-pcc@zfs sanity-pfl@ldiskfs+DNE sanity-pfl@zfs sanity-quota@ldiskfs+DNE sanity-quota@zfs sanity-scrub@ldiskfs+DNE sanity-scrub@zfs sanity-sec@ldiskfs+DNE sanity-sec@zfs sanityn@ldiskfs+DNE sanityn@zfs",
      "accounts_in_message": [],
      "_revision_number": 2
    },
    {
      "id": "b4325b033b8af7e8245cbedf56cb1e1ba200e232",
      "author": {
        "_account_id": 683,
        "name": "jenkins",
        "email": "devops@whamcloud.com",
        "username": "jenkins",
        "tags": [
          "SERVICE_USER"
        ]
      },
      "date": "2024-12-03 17:17:55.000000000",
      "message": "Patch Set 2: Verified+1\n\nBuild Successful \n\nhttps://build.whamcloud.com/job/lustre-reviews/109342/ : SUCCESS",
      "accounts_in_message": [],
      "_revision_number": 2
    },
    {
      "id": "f77978aec32ec367749d6d769c371754b434926e",
      "author": {
        "_account_id": 147,
        "name": "Maloo",
        "email": "maloo@whamcloud.com",
        "username": "maloo",
        "tags": [
          "SERVICE_USER"
        ]
      },
      "date": "2024-12-03 17:19:48.000000000",
      "message": "Patch Set 2:\n\nThe following sessions will be run for build 109342 patch 2\n\nEnforced:\n- review-ldiskfs-dne on el8.10-x86_64/ldiskfs servers and clients\n- review-ldiskfs-dne on el9.3-x86_64/ldiskfs servers and clients\n- review-dne-selinux-ssk-part-1 on el8.10-x86_64/ldiskfs servers and clients\n- review-dne-selinux-ssk-part-2 on el8.10-x86_64/ldiskfs servers and clients\n- custom on el8.10-x86_64/ldiskfs servers and clients\n\nOptional:\n- review-ldiskfs-dne-arm on el8.10-x86_64/ldiskfs servers and el9.3-aarch64/ldiskfs clients\n\nMaloo Test Queue: https://testing.whamcloud.com/test_queue?jobs=lustre-reviews&builds=109342&commit=Apply+Filter\nMaloo Results: https://testing.whamcloud.com/test_sessions/related?jobs=lustre-reviews&builds=109342#redirect",
      "accounts_in_message": [],
      "_revision_number": 2
    },
    {
      "id": "616fa939034752ba9dc0dede15de7788c46651c9",
      "author": {
        "_account_id": 799,
        "name": "Lustre Gerrit Janitor",
        "email": "lgerrit@linuxhacker.ru",
        "username": "lgerritjanitor",
        "tags": [
          "SERVICE_USER"
        ]
      },
      "date": "2024-12-03 19:26:31.000000000",
      "message": "Patch Set 2:\n\nEven though \"Test-Parameters: trivial\" was detected, this deeply suspicious bot still run some testing\n\nTesting has completed with errors!\n\n> racer@ldiskfs+DNE Timeout(1009s)\n\nSucceeded:\n- conf-sanity1@ldiskfs+DNE conf-sanity2@ldiskfs+DNE conf-sanity3@ldiskfs+DNE conf-sanity-slow@ldiskfs+DNE conf-sanity-slow-106@ldiskfs+DNE conf-sanity1@zfs conf-sanity2@zfs conf-sanity3@zfs conf-sanity-slow@zfs conf-sanity-slow-106@zfs insanity@ldiskfs+DNE insanity@zfs lnet-selftest@zfs lustre-rsync-test@ldiskfs+DNE lustre-rsync-test@zfs ost-pools@ldiskfs+DNE ost-pools@zfs pjdfstest@ldiskfs+DNE pjdfstest@zfs racer@zfs recovery-small@ldiskfs+DNE recovery-small@zfs replay-dual@ldiskfs+DNE replay-dual@zfs replay-ost-single@ldiskfs+DNE replay-ost-single@zfs replay-single@ldiskfs+DNE replay-single@zfs replay-vbr@ldiskfs+DNE replay-vbr@zfs sanity1@ldiskfs+DNE sanity2@ldiskfs+DNE sanity-slow@ldiskfs+DNE sanity1@zfs sanity2@zfs sanity-slow@zfs sanity-benchmark@ldiskfs+DNE sanity-benchmark@zfs sanity-dom@ldiskfs+DNE sanity-dom@zfs sanity-flr@ldiskfs+DNE sanity-flr@zfs sanity-hsm@ldiskfs+DNE sanity-hsm@zfs sanity-lfsck@ldiskfs+DNE sanity-lfsck@zfs sanity-lnet@zfs sanity-pcc@ldiskfs+DNE sanity-pcc@zfs sanity-pfl@ldiskfs+DNE sanity-pfl@zfs sanity-quota@ldiskfs+DNE sanity-quota@zfs sanity-scrub@ldiskfs+DNE sanity-scrub@zfs sanity-sec@ldiskfs+DNE sanity-sec@zfs sanityn@ldiskfs+DNE sanityn@zfs \n\n(centos7)All results and logs: https://testing.whamcloud.com/gerrit-janitor/47555/results.html",
      "accounts_in_message": [],
      "_revision_number": 2
    },
    {
      "id": "4b76188416ce63614229d5e35fda466b17d32874",
      "author": {
        "_account_id": 147,
        "name": "Maloo",
        "email": "maloo@whamcloud.com",
        "username": "maloo",
        "tags": [
          "SERVICE_USER"
        ]
      },
      "date": "2024-12-03 23:28:39.000000000",
      "message": "Patch Set 2: Verified+1\n\nPassed enforced test review-ldiskfs-dne on RHEL 8.10 / x86_64 uploaded by Onyx Autotest 2 from onyx-135vm7: https://testing.whamcloud.com/test_sessions/07dfad5c-4561-414b-b6f9-e432436191fc ran 5 tests.",
      "accounts_in_message": [],
      "_revision_number": 2
    },
    {
      "id": "1c79d84eec83207d0b1dc98bf11b0d3a699ca851",
      "author": {
        "_account_id": 793,
        "name": "Aurelien Degremont",
        "email": "adegremont@nvidia.com",
        "username": "degremoa"
      },
      "date": "2024-12-04 14:10:25.000000000",
      "message": "Patch Set 2:\n\n(2 comments)",
      "accounts_in_message": [],
      "_revision_number": 2
    },
    {
      "id": "08a28b49fc4f21eedeb9cda4b7e58407fb121664",
      "author": {
        "_account_id": 793,
        "name": "Aurelien Degremont",
        "email": "adegremont@nvidia.com",
        "username": "degremoa"
      },
      "date": "2024-12-04 15:13:55.000000000",
      "message": "Patch Set 2: Code-Review+1",
      "accounts_in_message": [],
      "_revision_number": 2
    },
    {
      "id": "e02a89a381a9e119b206a7c6b0da273629ca5c8e",
      "author": {
        "_account_id": 793,
        "name": "Aurelien Degremont",
        "email": "adegremont@nvidia.com",
        "username": "degremoa"
      },
      "date": "2024-12-05 08:59:29.000000000",
      "message": "Patch Set 2: -Code-Review\n\nWe see strange permission errors while testing this patch. Dropping +1 until this is understood.",
      "accounts_in_message": [],
      "_revision_number": 2
    },
    {
      "id": "716792fc8d0abc25962fd38d4ae8a60c705069ee",
      "tag": "autogenerated:gerrit:newPatchSet",
      "author": {
        "_account_id": 597,
        "name": "Sebastien Buisson",
        "email": "sbuisson@ddn.com",
        "username": "sbuisson"
      },
      "date": "2024-12-05 17:12:56.000000000",
      "message": "Uploaded patch set 3.",
      "accounts_in_message": [],
      "_revision_number": 3
    },
    {
      "id": "447cabd633e9c4dc3f025f30e8edf31da0ca6962",
      "author": {
        "_account_id": 597,
        "name": "Sebastien Buisson",
        "email": "sbuisson@ddn.com",
        "username": "sbuisson"
      },
      "date": "2024-12-05 17:14:24.000000000",
      "message": "Patch Set 3:\n\nMerge get_user_tgt_ccname() into lkrb5_prepare_user_cred().",
      "accounts_in_message": [],
      "_revision_number": 3
    },
    {
      "id": "7a00d701ae23af5636411a7dbd73c0f630c89daf",
      "author": {
        "_account_id": 377,
        "name": "wc-checkpatch",
        "username": "hpdd-checkpatch",
        "tags": [
          "SERVICE_USER"
        ]
      },
      "date": "2024-12-05 17:16:58.000000000",
      "message": "Patch Set 3:\n\nLooks good to me.",
      "accounts_in_message": [],
      "_revision_number": 3
    },
    {
      "id": "4333a1489c412ebbb36e3d1f712d14cef681021e",
      "author": {
        "_account_id": 793,
        "name": "Aurelien Degremont",
        "email": "adegremont@nvidia.com",
        "username": "degremoa"
      },
      "date": "2024-12-05 17:17:04.000000000",
      "message": "Patch Set 3: Code-Review+1\n\nThe issue we saw was identified. Not related to that patch.",
      "accounts_in_message": [],
      "_revision_number": 3
    },
    {
      "id": "66a7d51f34b39136a253984e65b986467c9d863d",
      "author": {
        "_account_id": 799,
        "name": "Lustre Gerrit Janitor",
        "email": "lgerrit@linuxhacker.ru",
        "username": "lgerritjanitor",
        "tags": [
          "SERVICE_USER"
        ]
      },
      "date": "2024-12-05 17:17:07.000000000",
      "message": "Patch Set 3:\n\n(1 comment)\n\nBuilds for x86_64 centos7,rhel8.5 successful\nJob output URL: https://testing.whamcloud.com/gerrit-janitor/47637/results.html\n\n Commencing initial testing: runtests@ldiskfs+DNE runtests-ssk@ldiskfs+SharedKey runtests@zfs",
      "accounts_in_message": [],
      "_revision_number": 3
    },
    {
      "id": "5ea3e7d2907fa39f5f34277255186b49b34a9c6d",
      "author": {
        "_account_id": 799,
        "name": "Lustre Gerrit Janitor",
        "email": "lgerrit@linuxhacker.ru",
        "username": "lgerritjanitor",
        "tags": [
          "SERVICE_USER"
        ]
      },
      "date": "2024-12-05 17:31:13.000000000",
      "message": "Patch Set 3:\n\nInitial testing succeeded.\n\nSucceeded:\n- runtests@ldiskfs+DNE runtests-ssk@ldiskfs+SharedKey runtests@zfs \n\n(centos7)All results and logs: https://testing.whamcloud.com/gerrit-janitor/47637/results.html\nCommencing standard testing: \n- conf-sanity1@ldiskfs+DNE conf-sanity2@ldiskfs+DNE conf-sanity3@ldiskfs+DNE conf-sanity-slow@ldiskfs+DNE conf-sanity-slow-106@ldiskfs+DNE conf-sanity1@zfs conf-sanity2@zfs conf-sanity3@zfs conf-sanity-slow@zfs conf-sanity-slow-106@zfs insanity@ldiskfs+DNE insanity@zfs lnet-selftest@zfs lustre-rsync-test@ldiskfs+DNE lustre-rsync-test@zfs ost-pools@ldiskfs+DNE ost-pools@zfs pjdfstest@ldiskfs+DNE pjdfstest@zfs racer@ldiskfs+DNE racer@zfs recovery-small@ldiskfs+DNE recovery-small@zfs replay-dual@ldiskfs+DNE replay-dual@zfs replay-ost-single@ldiskfs+DNE replay-ost-single@zfs replay-single@ldiskfs+DNE replay-single@zfs replay-vbr@ldiskfs+DNE replay-vbr@zfs sanity1@ldiskfs+DNE sanity2@ldiskfs+DNE sanity-slow@ldiskfs+DNE sanity1@zfs sanity2@zfs sanity-slow@zfs sanity-benchmark@ldiskfs+DNE sanity-benchmark@zfs sanity-dom@ldiskfs+DNE sanity-dom@zfs sanity-flr@ldiskfs+DNE sanity-flr@zfs sanity-hsm@ldiskfs+DNE sanity-hsm@zfs sanity-lfsck@ldiskfs+DNE sanity-lfsck@zfs sanity-lnet@zfs sanity-pcc@ldiskfs+DNE sanity-pcc@zfs sanity-pfl@ldiskfs+DNE sanity-pfl@zfs sanity-quota@ldiskfs+DNE sanity-quota@zfs sanity-scrub@ldiskfs+DNE sanity-scrub@zfs sanity-sec@ldiskfs+DNE sanity-sec@zfs sanityn@ldiskfs+DNE sanityn@zfs",
      "accounts_in_message": [],
      "_revision_number": 3
    },
    {
      "id": "666a37a7bf713b031d70c770ed10acf4add46fd9",
      "author": {
        "_account_id": 683,
        "name": "jenkins",
        "email": "devops@whamcloud.com",
        "username": "jenkins",
        "tags": [
          "SERVICE_USER"
        ]
      },
      "date": "2024-12-05 17:48:53.000000000",
      "message": "Patch Set 3: Verified+1\n\nBuild Successful \n\nhttps://build.whamcloud.com/job/lustre-reviews/109427/ : SUCCESS",
      "accounts_in_message": [],
      "_revision_number": 3
    },
    {
      "id": "b508668870cedf019e9de5b5f62137d20c143b3a",
      "author": {
        "_account_id": 147,
        "name": "Maloo",
        "email": "maloo@whamcloud.com",
        "username": "maloo",
        "tags": [
          "SERVICE_USER"
        ]
      },
      "date": "2024-12-05 17:50:11.000000000",
      "message": "Patch Set 3:\n\nThe following sessions will be run for build 109427 patch 3\n\nEnforced:\n- review-ldiskfs-dne on el8.10-x86_64/ldiskfs servers and clients\n- review-ldiskfs-dne on el9.3-x86_64/ldiskfs servers and clients\n- review-dne-selinux-ssk-part-1 on el8.10-x86_64/ldiskfs servers and clients\n- review-dne-selinux-ssk-part-2 on el8.10-x86_64/ldiskfs servers and clients\n- custom on el8.10-x86_64/ldiskfs servers and clients\n\nOptional:\n- review-ldiskfs-dne-arm on el8.10-x86_64/ldiskfs servers and el9.3-aarch64/ldiskfs clients\n\nMaloo Test Queue: https://testing.whamcloud.com/test_queue?jobs=lustre-reviews&builds=109427&commit=Apply+Filter\nMaloo Results: https://testing.whamcloud.com/test_sessions/related?jobs=lustre-reviews&builds=109427#redirect",
      "accounts_in_message": [],
      "_revision_number": 3
    },
    {
      "id": "116a2cb4e51ce614b1140b3f282562ef5a682b54",
      "author": {
        "_account_id": 799,
        "name": "Lustre Gerrit Janitor",
        "email": "lgerrit@linuxhacker.ru",
        "username": "lgerritjanitor",
        "tags": [
          "SERVICE_USER"
        ]
      },
      "date": "2024-12-05 23:07:33.000000000",
      "message": "Patch Set 3:\n\nEven though \"Test-Parameters: trivial\" was detected, this deeply suspicious bot still run some testing\n\nTesting has completed Successfully\n\nSucceeded:\n- conf-sanity1@ldiskfs+DNE conf-sanity2@ldiskfs+DNE conf-sanity3@ldiskfs+DNE conf-sanity-slow@ldiskfs+DNE conf-sanity-slow-106@ldiskfs+DNE conf-sanity1@zfs conf-sanity2@zfs conf-sanity3@zfs conf-sanity-slow@zfs conf-sanity-slow-106@zfs insanity@ldiskfs+DNE insanity@zfs lnet-selftest@zfs lustre-rsync-test@ldiskfs+DNE lustre-rsync-test@zfs ost-pools@ldiskfs+DNE ost-pools@zfs pjdfstest@ldiskfs+DNE pjdfstest@zfs racer@ldiskfs+DNE racer@zfs recovery-small@ldiskfs+DNE recovery-small@zfs replay-dual@ldiskfs+DNE replay-dual@zfs replay-ost-single@ldiskfs+DNE replay-ost-single@zfs replay-single@ldiskfs+DNE replay-single@zfs replay-vbr@ldiskfs+DNE replay-vbr@zfs sanity1@ldiskfs+DNE sanity2@ldiskfs+DNE sanity-slow@ldiskfs+DNE sanity1@zfs sanity2@zfs sanity-slow@zfs sanity-benchmark@ldiskfs+DNE sanity-benchmark@zfs sanity-dom@ldiskfs+DNE sanity-dom@zfs sanity-flr@ldiskfs+DNE sanity-flr@zfs sanity-hsm@ldiskfs+DNE sanity-hsm@zfs sanity-lfsck@ldiskfs+DNE sanity-lfsck@zfs sanity-lnet@zfs sanity-pcc@ldiskfs+DNE sanity-pcc@zfs sanity-pfl@ldiskfs+DNE sanity-pfl@zfs sanity-quota@ldiskfs+DNE sanity-quota@zfs sanity-scrub@ldiskfs+DNE sanity-scrub@zfs sanity-sec@ldiskfs+DNE sanity-sec@zfs sanityn@ldiskfs+DNE sanityn@zfs \n\n(centos7)All results and logs: https://testing.whamcloud.com/gerrit-janitor/47637/results.html",
      "accounts_in_message": [],
      "_revision_number": 3
    },
    {
      "id": "fcb7c86a15891d939d68c3fb631d112bf4abb383",
      "author": {
        "_account_id": 147,
        "name": "Maloo",
        "email": "maloo@whamcloud.com",
        "username": "maloo",
        "tags": [
          "SERVICE_USER"
        ]
      },
      "date": "2024-12-06 01:33:29.000000000",
      "message": "Patch Set 3: Verified+1\n\nPassed enforced test review-dne-selinux-ssk-part-1 on RHEL 8.10 / x86_64 uploaded by Onyx Autotest 2 from onyx-148vm1: https://testing.whamcloud.com/test_sessions/a85ae087-f44a-4ffe-9188-1a91c58cf31d ran 3 tests.",
      "accounts_in_message": [],
      "_revision_number": 3
    },
    {
      "id": "e48cf473be62c49e3719451099685b79ff2bdb5d",
      "author": {
        "_account_id": 117,
        "name": "Andreas Dilger",
        "email": "adilger@thelustrecollective.com",
        "username": "adilger"
      },
      "date": "2024-12-07 20:36:15.000000000",
      "message": "Patch Set 3: Code-Review+1",
      "accounts_in_message": [],
      "_revision_number": 3
    },
    {
      "id": "5ab36b826cbe7e7acadaf3c3c80de8d80bbedaae",
      "author": {
        "_account_id": 112,
        "name": "Oleg Drokin",
        "email": "green@whamcloud.com",
        "username": "green"
      },
      "date": "2024-12-16 08:19:33.000000000",
      "message": "Patch Set 3: Code-Review+2",
      "accounts_in_message": [],
      "_revision_number": 3
    },
    {
      "id": "3912f81340ef081adc7e61b7082f095b0baa6968",
      "tag": "autogenerated:gerrit:merged",
      "author": {
        "_account_id": 112,
        "name": "Oleg Drokin",
        "email": "green@whamcloud.com",
        "username": "green"
      },
      "date": "2024-12-16 08:19:38.000000000",
      "message": "Change has been successfully cherry-picked as 6791fbc530ad64d5764882f4c866ee2a42a3f1fc by Oleg Drokin",
      "accounts_in_message": [],
      "_revision_number": 4
    }
  ],
  "current_revision_number": 4,
  "current_revision": "6791fbc530ad64d5764882f4c866ee2a42a3f1fc",
  "revisions": {
    "6791fbc530ad64d5764882f4c866ee2a42a3f1fc": {
      "kind": "TRIVIAL_REBASE_WITH_MESSAGE_UPDATE",
      "_number": 4,
      "created": "2024-12-16 08:19:38.000000000",
      "uploader": {
        "_account_id": 112,
        "name": "Oleg Drokin",
        "email": "green@whamcloud.com",
        "username": "green"
      },
      "ref": "refs/changes/92/57192/4",
      "fetch": {
        "anonymous http": {
          "url": "https://review.whamcloud.com/fs/lustre-release",
          "ref": "refs/changes/92/57192/4"
        }
      },
      "commit": {
        "parents": [
          {
            "commit": "68dd4f2ba984d42356e0bfb9948223509d8407ca",
            "subject": "LU-17251 tests: increase parallel-scale OST seq_width"
          }
        ],
        "author": {
          "name": "Sebastien Buisson",
          "email": "sbuisson@ddn.com",
          "date": "2024-12-03 11:10:26.000000000",
          "tz": 60
        },
        "committer": {
          "name": "Oleg Drokin",
          "email": "green@whamcloud.com",
          "date": "2024-12-16 08:19:38.000000000",
          "tz": 0
        },
        "subject": "LU-18497 gss: carry out creds prepare as user",
        "message": "LU-18497 gss: carry out creds prepare as user\n\nInstead of forking a child process that switches to user identity to\nget the credentials cache name, just carry out the whole credentials\npreparation as the user, and switch back to original uid/gid in order\nto proceed to ioctls, eliminating the need to map memory between\nprocesses.\n\nTest-Parameters: trivial\nTest-Parameters: testgroup=review-dne-selinux-ssk-part-1\nTest-Parameters: testgroup=review-dne-selinux-ssk-part-2\nTest-Parameters: kerberos=true testlist=sanity-krb5\nSigned-off-by: Sebastien Buisson <sbuisson@ddn.com>\nChange-Id: I7807263d71cd3fc8a9934cc4c4da8b497b845e6f\nReviewed-on: https://review.whamcloud.com/c/fs/lustre-release/+/57192\nReviewed-by: Aurelien Degremont <adegremont@nvidia.com>\nReviewed-by: Andreas Dilger <adilger@whamcloud.com>\nReviewed-by: Oleg Drokin <green@whamcloud.com>\nTested-by: jenkins <devops@whamcloud.com>\nTested-by: Maloo <maloo@whamcloud.com>\n"
      },
      "branch": "refs/heads/master"
    }
  },
  "requirements": [],
  "submit_records": [
    {
      "status": "CLOSED",
      "labels": [
        {
          "label": "Verified",
          "status": "OK",
          "applied_by": {
            "_account_id": 147,
            "name": "Maloo",
            "email": "maloo@whamcloud.com",
            "username": "maloo",
            "tags": [
              "SERVICE_USER"
            ]
          }
        },
        {
          "label": "Code-Review",
          "status": "OK",
          "applied_by": {
            "_account_id": 112,
            "name": "Oleg Drokin",
            "email": "green@whamcloud.com",
            "username": "green"
          }
        }
      ]
    }
  ]
}