{
  "id": "fs%2Flustre-release~64511",
  "triplet_id": "fs%2Flustre-release~master~I1da27481bd609ba93ca4736a9bddb6a58e6e6371",
  "project": "fs/lustre-release",
  "branch": "master",
  "topic": "upstream",
  "attention_set": {},
  "removed_from_attention_set": {
    "125": {
      "account": {
        "_account_id": 125,
        "name": "James Simmons",
        "email": "jsimmons@infradead.org",
        "username": "jsimmons"
      },
      "last_update": "2026-03-31 05:32:22.000000000",
      "reason": "Change was submitted"
    },
    "655": {
      "account": {
        "_account_id": 655,
        "name": "Arshad Hussain",
        "email": "arshad.hussain@aeoncomputing.com",
        "username": "arshad512"
      },
      "last_update": "2026-03-31 05:32:22.000000000",
      "reason": "Change was submitted"
    },
    "808": {
      "account": {
        "_account_id": 808,
        "name": "Shaun Tancheff",
        "email": "shaun.tancheff@hpe.com",
        "username": "stancheff"
      },
      "last_update": "2026-03-31 05:32:22.000000000",
      "reason": "Change was submitted"
    },
    "117": {
      "account": {
        "_account_id": 117,
        "name": "Andreas Dilger",
        "email": "adilger@thelustrecollective.com",
        "username": "adilger"
      },
      "last_update": "2026-03-14 09:40:10.000000000",
      "reason": "<GERRIT_ACCOUNT_117> replied on the change",
      "reason_account": {
        "_account_id": 117,
        "name": "Andreas Dilger",
        "email": "adilger@thelustrecollective.com",
        "username": "adilger"
      }
    },
    "112": {
      "account": {
        "_account_id": 112,
        "name": "Oleg Drokin",
        "email": "green@whamcloud.com",
        "username": "green"
      },
      "last_update": "2026-03-31 05:32:19.000000000",
      "reason": "removed on reply"
    },
    "931": {
      "account": {
        "_account_id": 931,
        "name": "Timothy Day",
        "email": "timday@thelustrecollective.com",
        "username": "timday"
      },
      "last_update": "2026-03-14 02:19:16.000000000",
      "reason": "<GERRIT_ACCOUNT_931> replied on the change",
      "reason_account": {
        "_account_id": 931,
        "name": "Timothy Day",
        "email": "timday@thelustrecollective.com",
        "username": "timday"
      }
    }
  },
  "hashtags": [],
  "change_id": "I1da27481bd609ba93ca4736a9bddb6a58e6e6371",
  "subject": "LU-19179 lustre: remove remaining 4.X kernel support",
  "status": "MERGED",
  "created": "2026-03-11 23:59:33.000000000",
  "updated": "2026-03-31 17:17:22.000000000",
  "submitted": "2026-03-31 05:32:22.000000000",
  "submitter": {
    "_account_id": 112,
    "name": "Oleg Drokin",
    "email": "green@whamcloud.com",
    "username": "green"
  },
  "insertions": 136,
  "deletions": 792,
  "total_comment_count": 6,
  "unresolved_comment_count": 1,
  "has_review_started": true,
  "submission_id": "64511-upstream",
  "meta_rev_id": "3ac8822a91285a5fa35f99a9a7d0539565b50a78",
  "_number": 64511,
  "virtual_id_number": 64511,
  "owner": {
    "_account_id": 125,
    "name": "James Simmons",
    "email": "jsimmons@infradead.org",
    "username": "jsimmons"
  },
  "labels": {
    "Verified": {
      "all": [
        {
          "tag": "autogenerated:gerrit:merged",
          "value": 1,
          "date": "2026-03-31 05:32:22.000000000",
          "permitted_voting_range": {
            "min": 1,
            "max": 1
          },
          "_account_id": 683,
          "name": "jenkins",
          "email": "devops@whamcloud.com",
          "username": "jenkins",
          "tags": [
            "SERVICE_USER"
          ]
        },
        {
          "value": 0,
          "_account_id": 117,
          "name": "Andreas Dilger",
          "email": "adilger@thelustrecollective.com",
          "username": "adilger"
        },
        {
          "value": 0,
          "_account_id": 112,
          "name": "Oleg Drokin",
          "email": "green@whamcloud.com",
          "username": "green"
        },
        {
          "tag": "autogenerated:gerrit:merged",
          "value": 1,
          "date": "2026-03-31 05:32:22.000000000",
          "permitted_voting_range": {
            "min": 1,
            "max": 1
          },
          "_account_id": 147,
          "name": "Maloo",
          "email": "maloo@whamcloud.com",
          "username": "maloo",
          "tags": [
            "SERVICE_USER"
          ]
        },
        {
          "value": 0,
          "_account_id": 931,
          "name": "Timothy Day",
          "email": "timday@thelustrecollective.com",
          "username": "timday"
        }
      ],
      "values": {
        "-1": "Fails",
        " 0": "No score",
        "+1": "Verified"
      },
      "description": "",
      "default_value": 0
    },
    "Code-Review": {
      "all": [
        {
          "value": 0,
          "_account_id": 683,
          "name": "jenkins",
          "email": "devops@whamcloud.com",
          "username": "jenkins",
          "tags": [
            "SERVICE_USER"
          ]
        },
        {
          "tag": "autogenerated:gerrit:merged",
          "value": 1,
          "date": "2026-03-31 05:32:22.000000000",
          "permitted_voting_range": {
            "min": 1,
            "max": 1
          },
          "_account_id": 117,
          "name": "Andreas Dilger",
          "email": "adilger@thelustrecollective.com",
          "username": "adilger"
        },
        {
          "tag": "autogenerated:gerrit:merged",
          "value": 2,
          "date": "2026-03-31 05:32:22.000000000",
          "permitted_voting_range": {
            "min": 2,
            "max": 2
          },
          "_account_id": 112,
          "name": "Oleg Drokin",
          "email": "green@whamcloud.com",
          "username": "green"
        },
        {
          "value": 0,
          "_account_id": 147,
          "name": "Maloo",
          "email": "maloo@whamcloud.com",
          "username": "maloo",
          "tags": [
            "SERVICE_USER"
          ]
        },
        {
          "tag": "autogenerated:gerrit:merged",
          "value": 1,
          "date": "2026-03-31 05:32:22.000000000",
          "permitted_voting_range": {
            "min": 1,
            "max": 1
          },
          "_account_id": 931,
          "name": "Timothy Day",
          "email": "timday@thelustrecollective.com",
          "username": "timday"
        }
      ],
      "values": {
        "-2": "Do not submit",
        "-1": "I would prefer that you didn't submit this",
        " 0": "No score",
        "+1": "Looks good to me, but someone else must approve",
        "+2": "Looks good to me, approved"
      },
      "description": "",
      "default_value": 0
    }
  },
  "removable_reviewers": [
    {
      "_account_id": 655,
      "name": "Arshad Hussain",
      "email": "arshad.hussain@aeoncomputing.com",
      "username": "arshad512"
    },
    {
      "_account_id": 808,
      "name": "Shaun Tancheff",
      "email": "shaun.tancheff@hpe.com",
      "username": "stancheff"
    }
  ],
  "reviewers": {
    "REVIEWER": [
      {
        "_account_id": 112,
        "name": "Oleg Drokin",
        "email": "green@whamcloud.com",
        "username": "green"
      },
      {
        "_account_id": 117,
        "name": "Andreas Dilger",
        "email": "adilger@thelustrecollective.com",
        "username": "adilger"
      },
      {
        "_account_id": 147,
        "name": "Maloo",
        "email": "maloo@whamcloud.com",
        "username": "maloo",
        "tags": [
          "SERVICE_USER"
        ]
      },
      {
        "_account_id": 655,
        "name": "Arshad Hussain",
        "email": "arshad.hussain@aeoncomputing.com",
        "username": "arshad512"
      },
      {
        "_account_id": 683,
        "name": "jenkins",
        "email": "devops@whamcloud.com",
        "username": "jenkins",
        "tags": [
          "SERVICE_USER"
        ]
      },
      {
        "_account_id": 808,
        "name": "Shaun Tancheff",
        "email": "shaun.tancheff@hpe.com",
        "username": "stancheff"
      },
      {
        "_account_id": 931,
        "name": "Timothy Day",
        "email": "timday@thelustrecollective.com",
        "username": "timday"
      }
    ],
    "CC": [
      {
        "_account_id": 377,
        "name": "wc-checkpatch",
        "username": "hpdd-checkpatch",
        "tags": [
          "SERVICE_USER"
        ]
      },
      {
        "_account_id": 403,
        "name": "Autotest",
        "email": "autotest@whamcloud.com",
        "username": "autotest",
        "tags": [
          "SERVICE_USER"
        ]
      },
      {
        "_account_id": 549,
        "name": "Misc Code Checks Robot (Gatekeeper helper)",
        "username": "smatchreview",
        "tags": [
          "SERVICE_USER"
        ]
      },
      {
        "_account_id": 799,
        "name": "Lustre Gerrit Janitor",
        "email": "lgerrit@linuxhacker.ru",
        "username": "lgerritjanitor",
        "tags": [
          "SERVICE_USER"
        ]
      }
    ]
  },
  "pending_reviewers": {},
  "messages": [
    {
      "id": "96b34f73823d0ad3fd4380a68a7940f50d8e019b",
      "tag": "autogenerated:gerrit:newPatchSet",
      "author": {
        "_account_id": 125,
        "name": "James Simmons",
        "email": "jsimmons@infradead.org",
        "username": "jsimmons"
      },
      "date": "2026-03-11 23:59:33.000000000",
      "message": "Uploaded patch set 1.",
      "accounts_in_message": [],
      "_revision_number": 1
    },
    {
      "id": "f8f451f2dee8ce465e8c6df46368974f3bbf130c",
      "tag": "autogenerated:gerrit:newPatchSet",
      "author": {
        "_account_id": 125,
        "name": "James Simmons",
        "email": "jsimmons@infradead.org",
        "username": "jsimmons"
      },
      "date": "2026-03-12 00:00:23.000000000",
      "message": "Uploaded patch set 2: Commit message was updated.",
      "accounts_in_message": [],
      "_revision_number": 2
    },
    {
      "id": "6af6f42ed3c14be4e597db97ee0b207edf44a3e6",
      "author": {
        "_account_id": 683,
        "name": "jenkins",
        "email": "devops@whamcloud.com",
        "username": "jenkins",
        "tags": [
          "SERVICE_USER"
        ]
      },
      "date": "2026-03-12 00:00:24.000000000",
      "message": "Patch Set 1:\n\nNo Builds Executed",
      "accounts_in_message": [],
      "_revision_number": 1
    },
    {
      "id": "947169baee0ab8d2932cd50bd6e803542bcb7a4b",
      "author": {
        "_account_id": 799,
        "name": "Lustre Gerrit Janitor",
        "email": "lgerrit@linuxhacker.ru",
        "username": "lgerritjanitor",
        "tags": [
          "SERVICE_USER"
        ]
      },
      "date": "2026-03-12 00:03:19.000000000",
      "message": "Patch Set 1:\n\nNewer revision detected, aborting all work on revision 1",
      "accounts_in_message": [],
      "_revision_number": 1
    },
    {
      "id": "4493de084a73e8f35df46491cf60105122f85f20",
      "author": {
        "_account_id": 549,
        "name": "Misc Code Checks Robot (Gatekeeper helper)",
        "username": "smatchreview",
        "tags": [
          "SERVICE_USER"
        ]
      },
      "date": "2026-03-12 00:03:42.000000000",
      "message": "Patch Set 1:\n\nCode-wise looks good to me.",
      "accounts_in_message": [],
      "_revision_number": 1
    },
    {
      "id": "8d54971c9ea826e1b328f38d9346feec436c6364",
      "author": {
        "_account_id": 377,
        "name": "wc-checkpatch",
        "username": "hpdd-checkpatch",
        "tags": [
          "SERVICE_USER"
        ]
      },
      "date": "2026-03-12 00:06:38.000000000",
      "message": "Patch Set 2:\n\nLooks good to me.",
      "accounts_in_message": [],
      "_revision_number": 2
    },
    {
      "id": "7e481d757313f54bffcd121ffa8f3f6fcc4da914",
      "author": {
        "_account_id": 799,
        "name": "Lustre Gerrit Janitor",
        "email": "lgerrit@linuxhacker.ru",
        "username": "lgerritjanitor",
        "tags": [
          "SERVICE_USER"
        ]
      },
      "date": "2026-03-12 00:10:50.000000000",
      "message": "Patch Set 2:\n\nBuilds for x86_64 rocky8.10,rocky9.6 successful\nJob output URL: https://testing.whamcloud.com/gerrit-janitor/61068/results.html\n\n Commencing initial testing: runtests@ldiskfs+DNE runtests-ssk@ldiskfs+SharedKey runtests@zfs",
      "accounts_in_message": [],
      "_revision_number": 2
    },
    {
      "id": "078ad415bd907bd301bb033034b00c0efab8db87",
      "author": {
        "_account_id": 549,
        "name": "Misc Code Checks Robot (Gatekeeper helper)",
        "username": "smatchreview",
        "tags": [
          "SERVICE_USER"
        ]
      },
      "date": "2026-03-12 00:13:29.000000000",
      "message": "Patch Set 2:\n\nCode-wise looks good to me.",
      "accounts_in_message": [],
      "_revision_number": 2
    },
    {
      "id": "804c3a884a0af3b04d94fc0060961043f9a17dff",
      "author": {
        "_account_id": 799,
        "name": "Lustre Gerrit Janitor",
        "email": "lgerrit@linuxhacker.ru",
        "username": "lgerritjanitor",
        "tags": [
          "SERVICE_USER"
        ]
      },
      "date": "2026-03-12 00:20:05.000000000",
      "message": "Patch Set 2:\n\nInitial testing succeeded.\n\nSucceeded:\n- runtests@ldiskfs+DNE runtests-ssk@ldiskfs+SharedKey runtests@zfs \n\n(rocky8.10)All results and logs: https://testing.whamcloud.com/gerrit-janitor/61068/results.html\nCommencing standard testing: \n- conf-sanity1@ldiskfs+DNE conf-sanity2@ldiskfs+DNE conf-sanity3@ldiskfs+DNE conf-sanity4@ldiskfs+DNE conf-sanity-slow@ldiskfs+DNE conf-sanity-slow-106@ldiskfs+DNE conf-sanity1@zfs conf-sanity2@zfs conf-sanity3@zfs conf-sanity4@zfs conf-sanity-slow@zfs conf-sanity-slow-106@zfs insanity@ldiskfs+DNE insanity@zfs lnet-selftest@zfs lustre-rsync-test@ldiskfs+DNE lustre-rsync-test@zfs ost-pools@ldiskfs+DNE ost-pools@zfs pjdfstest@ldiskfs+DNE pjdfstest@zfs racer@ldiskfs+DNE racer@zfs recovery-small@ldiskfs+DNE recovery-small@zfs replay-dual@ldiskfs+DNE replay-dual@zfs replay-ost-single@ldiskfs+DNE replay-ost-single@zfs replay-single1@ldiskfs+DNE replay-single2@ldiskfs+DNE replay-single1@zfs replay-single2@zfs replay-vbr@ldiskfs+DNE replay-vbr@zfs sanity1@ldiskfs+DNE sanity2@ldiskfs+DNE sanity3@ldiskfs+DNE sanity-slow@ldiskfs+DNE sanity1@zfs sanity2@zfs sanity3@zfs sanity-slow@zfs sanity-benchmark@ldiskfs+DNE sanity-benchmark@zfs sanity-dom@ldiskfs+DNE sanity-dom@zfs sanity-flr@ldiskfs+DNE sanity-flr@zfs sanity-hsm@ldiskfs+DNE sanity-hsm@zfs sanity-lfsck@ldiskfs+DNE sanity-lfsck@zfs sanity-lnet@zfs sanity-pcc@ldiskfs+DNE sanity-pcc@zfs sanity-pfl@ldiskfs+DNE sanity-pfl@zfs sanity-quota@ldiskfs+DNE sanity-quota@zfs sanity-scrub@ldiskfs+DNE sanity-scrub@zfs sanity-sec@ldiskfs+DNE sanity-sec@zfs sanityn@ldiskfs+DNE sanityn@zfs",
      "accounts_in_message": [],
      "_revision_number": 2
    },
    {
      "id": "650ab1b60c77b3806547bfacdbe94c9c94bda6e3",
      "author": {
        "_account_id": 683,
        "name": "jenkins",
        "email": "devops@whamcloud.com",
        "username": "jenkins",
        "tags": [
          "SERVICE_USER"
        ]
      },
      "date": "2026-03-12 00:28:04.000000000",
      "message": "Patch Set 2: Verified+1\n\nBuild Successful \n\nhttps://build.whamcloud.com/job/lustre-reviews/122352/ : SUCCESS",
      "accounts_in_message": [],
      "_revision_number": 2
    },
    {
      "id": "3e3cb8cc98944e850010b30c8d5691edbeda84b6",
      "author": {
        "_account_id": 147,
        "name": "Maloo",
        "email": "maloo@whamcloud.com",
        "username": "maloo",
        "tags": [
          "SERVICE_USER"
        ]
      },
      "date": "2026-03-12 00:30:34.000000000",
      "message": "Patch Set 2:\n\n#### The following sessions will be run for Build 122352 (patch #2):\n\n#### Enforced:\n\n- review-zfs on el8.10-x86_64/el8.10-x86_64/zfs/zfs\n\n- review-dne-part-1 on el8.10-x86_64/el8.10-x86_64/ldiskfs/ldiskfs\n\n- review-dne-part-2 on el8.10-x86_64/el8.10-x86_64/ldiskfs/ldiskfs\n\n- review-dne-part-3 on el8.10-x86_64/el8.10-x86_64/ldiskfs/ldiskfs\n\n- review-dne-part-4 on el8.10-x86_64/el8.10-x86_64/ldiskfs/ldiskfs\n\n- review-dne-part-5 on el8.10-x86_64/el8.10-x86_64/ldiskfs/ldiskfs\n\n- review-dne-part-6 on el8.10-x86_64/el8.10-x86_64/ldiskfs/ldiskfs\n\n- review-dne-part-7 on el8.10-x86_64/el8.10-x86_64/ldiskfs/ldiskfs\n\n- review-dne-part-8 on el8.10-x86_64/el8.10-x86_64/ldiskfs/ldiskfs\n\n- review-dne-zfs-part-1 on el8.10-x86_64/el8.10-x86_64/zfs/zfs\n\n- review-dne-zfs-part-2 on el8.10-x86_64/el8.10-x86_64/zfs/zfs\n\n- review-dne-zfs-part-3 on el8.10-x86_64/el8.10-x86_64/zfs/zfs\n\n- review-dne-zfs-part-4 on el8.10-x86_64/el8.10-x86_64/zfs/zfs\n\n- review-dne-zfs-part-5 on el8.10-x86_64/el8.10-x86_64/zfs/zfs\n\n- review-dne-zfs-part-6 on el8.10-x86_64/el8.10-x86_64/zfs/zfs\n\n- review-dne-zfs-part-7 on el8.10-x86_64/el8.10-x86_64/zfs/zfs\n\n- review-dne-part-1 on el9.5-x86_64/el9.5-x86_64/ldiskfs/ldiskfs\n\n- review-dne-part-2 on el9.5-x86_64/el9.5-x86_64/ldiskfs/ldiskfs\n\n- review-dne-part-3 on el9.5-x86_64/el9.5-x86_64/ldiskfs/ldiskfs\n\n- review-dne-part-4 on el9.5-x86_64/el9.5-x86_64/ldiskfs/ldiskfs\n\n- review-dne-part-5 on el9.5-x86_64/el9.5-x86_64/ldiskfs/ldiskfs\n\n- review-dne-part-6 on el9.5-x86_64/el9.5-x86_64/ldiskfs/ldiskfs\n\n- review-dne-part-7 on el9.5-x86_64/el9.5-x86_64/ldiskfs/ldiskfs\n\n- review-dne-part-8 on el9.5-x86_64/el9.5-x86_64/ldiskfs/ldiskfs\n\n- review-dne-selinux-ssk-part-1 on el8.10-x86_64/el8.10-x86_64/ldiskfs/ldiskfs\n\n- review-dne-selinux-ssk-part-2 on el8.10-x86_64/el8.10-x86_64/ldiskfs/ldiskfs\n\n- review-ldiskfs on el8.10-x86_64/el9.5-x86_64/ldiskfs/ldiskfs\n\n- review-ldiskfs on el8.10-x86_64/sles15sp5-x86_64/ldiskfs/ldiskfs\n\n- review-ldiskfs-ubuntu on el8.10-x86_64/ubuntu2204-x86_64/ldiskfs/ldiskfs\n\n- review-ldiskfs-ubuntu on el8.10-x86_64/ubuntu2404-x86_64/ldiskfs/ldiskfs\n\n#### Optional:\n\n- review-dne-part-9 on el8.10-x86_64/el8.10-x86_64/ldiskfs/ldiskfs\n\n- review-dne-part-1 on el9.6-x86_64/el9.6-x86_64/ldiskfs/ldiskfs\n\n- review-dne-part-2 on el9.6-x86_64/el9.6-x86_64/ldiskfs/ldiskfs\n\n- review-dne-part-3 on el9.6-x86_64/el9.6-x86_64/ldiskfs/ldiskfs\n\n- review-dne-part-4 on el9.6-x86_64/el9.6-x86_64/ldiskfs/ldiskfs\n\n- review-dne-part-5 on el9.6-x86_64/el9.6-x86_64/ldiskfs/ldiskfs\n\n- review-dne-part-6 on el9.6-x86_64/el9.6-x86_64/ldiskfs/ldiskfs\n\n- review-dne-part-7 on el9.6-x86_64/el9.6-x86_64/ldiskfs/ldiskfs\n\n- review-dne-part-8 on el9.6-x86_64/el9.6-x86_64/ldiskfs/ldiskfs\n\n- review-dne-part-9 on el9.6-x86_64/el9.6-x86_64/ldiskfs/ldiskfs\n\n- review-dne-part-9 on el9.5-x86_64/el9.5-x86_64/ldiskfs/ldiskfs\n\n- review-ldiskfs-arm on el8.10-x86_64/rocky9.5-aarch64/ldiskfs/ldiskfs\n\n- review-ldiskfs on el8.10-x86_64/el9.6-x86_64/ldiskfs/ldiskfs\n\n- review-ldiskfs on el8.10-x86_64/el9.7-x86_64/ldiskfs/ldiskfs\n\n- review-ldiskfs on el8.10-x86_64/el10.0-x86_64/ldiskfs/ldiskfs\n\n- review-ldiskfs on el8.10-x86_64/el10.1-x86_64/ldiskfs/ldiskfs\n\n- review-dne-ipv6 on el8.10-x86_64/el8.10-x86_64/ldiskfs/ldiskfs\n\n- review-dne-ipv6 on el9.5-x86_64/el9.5-x86_64/ldiskfs/ldiskfs\n\n---\n\nMaloo Test Queue: https://testing.whamcloud.com/test_queue?jobs=lustre-reviews&builds=122352&commit=Apply+Filter\n\nMaloo Results: https://testing.whamcloud.com/test_sessions/related?jobs=lustre-reviews&builds=122352#redirect",
      "accounts_in_message": [],
      "_revision_number": 2
    },
    {
      "id": "b005df01351dcb2c25311aa8f47fa3968896d85d",
      "author": {
        "_account_id": 799,
        "name": "Lustre Gerrit Janitor",
        "email": "lgerrit@linuxhacker.ru",
        "username": "lgerritjanitor",
        "tags": [
          "SERVICE_USER"
        ]
      },
      "date": "2026-03-12 05:28:21.000000000",
      "message": "Patch Set 2:\n\nTesting has completed with errors!\n\n> replay-single2@ldiskfs+DNE Failure(4511s)\n- 135(Unexpected sync success) \n> sanity2@ldiskfs+DNE Timeout(9650s)\n- (Crash processing failed with code 1 stdout: Usage: ./scripts/extract_crash_data.sh builddir corefile distro arch\n stderr: )(Usage: ./scripts/extract_crash_data.sh builddir corefile distro arch\n)\n> sanity2@zfs Timeout(8718s)\n- (Crash processing failed with code 1 stdout: Usage: ./scripts/extract_crash_data.sh builddir corefile distro arch\n stderr: )(Usage: ./scripts/extract_crash_data.sh builddir corefile distro arch\n)\n> sanity-pcc@ldiskfs+DNE Failure(3358s)\n- 1c(expected /mnt/pcc.d1c.sanity-pcc/d1c.sanity-pcc/0bd3/0x200000bd1:0x2:0x0 size: 7654321 got: 0) 1d(expected /mnt/pcc.d1d.sanity-pcc/d1d.sanity-pcc/13a3/0x2000013a1:0x2:0x0 size: 7654321 got: 0) \n> sanity-pcc@zfs Failure(2777s)\n- 1c(expected /mnt/pcc.d1c.sanity-pcc/d1c.sanity-pcc/0bd3/0x200000bd1:0x2:0x0 size: 7654321 got: 0) 1d(/mnt/lustre/d1d.sanity-pcc/f1d.sanity-pcc expected pcc state: readwrite, but got: none) \n\nSucceeded:\n- conf-sanity1@ldiskfs+DNE conf-sanity2@ldiskfs+DNE conf-sanity3@ldiskfs+DNE conf-sanity4@ldiskfs+DNE conf-sanity-slow@ldiskfs+DNE conf-sanity-slow-106@ldiskfs+DNE conf-sanity1@zfs conf-sanity2@zfs conf-sanity3@zfs conf-sanity4@zfs conf-sanity-slow@zfs conf-sanity-slow-106@zfs insanity@ldiskfs+DNE insanity@zfs lnet-selftest@zfs lustre-rsync-test@ldiskfs+DNE lustre-rsync-test@zfs ost-pools@ldiskfs+DNE ost-pools@zfs pjdfstest@ldiskfs+DNE pjdfstest@zfs racer@ldiskfs+DNE racer@zfs recovery-small@ldiskfs+DNE recovery-small@zfs replay-dual@ldiskfs+DNE replay-dual@zfs replay-ost-single@ldiskfs+DNE replay-ost-single@zfs replay-single1@ldiskfs+DNE replay-single1@zfs replay-single2@zfs replay-vbr@ldiskfs+DNE replay-vbr@zfs sanity1@ldiskfs+DNE sanity3@ldiskfs+DNE sanity-slow@ldiskfs+DNE sanity1@zfs sanity3@zfs sanity-slow@zfs sanity-benchmark@ldiskfs+DNE sanity-benchmark@zfs sanity-dom@ldiskfs+DNE sanity-dom@zfs sanity-flr@ldiskfs+DNE sanity-flr@zfs sanity-hsm@ldiskfs+DNE sanity-hsm@zfs sanity-lfsck@ldiskfs+DNE sanity-lfsck@zfs sanity-lnet@zfs sanity-pfl@ldiskfs+DNE sanity-pfl@zfs sanity-quota@ldiskfs+DNE sanity-quota@zfs sanity-scrub@ldiskfs+DNE sanity-scrub@zfs sanity-sec@ldiskfs+DNE sanity-sec@zfs sanityn@ldiskfs+DNE sanityn@zfs \n\n(rocky8.10)All results and logs: https://testing.whamcloud.com/gerrit-janitor/61068/results.html",
      "accounts_in_message": [],
      "_revision_number": 2
    },
    {
      "id": "e0783f853c2ea29dddcb925bbd808b9294316549",
      "author": {
        "_account_id": 147,
        "name": "Maloo",
        "email": "maloo@whamcloud.com",
        "username": "maloo",
        "tags": [
          "SERVICE_USER"
        ]
      },
      "date": "2026-03-12 05:45:27.000000000",
      "message": "Patch Set 2:\n\nFailed enforced test review-dne-part-5 on RHEL 8.10 / x86_64 uploaded by Onyx Autotest from onyx-146vm1: https://testing.whamcloud.com/test_sessions/5ad3daf8-c39c-44fa-92c7-795af66ab833 ran 5 tests.  1 tests failed: lustre-rsync-test.",
      "accounts_in_message": [],
      "_revision_number": 2
    },
    {
      "id": "3f60aba89964634d85902eb11b93943f4b1e56ab",
      "author": {
        "_account_id": 147,
        "name": "Maloo",
        "email": "maloo@whamcloud.com",
        "username": "maloo",
        "tags": [
          "SERVICE_USER"
        ]
      },
      "date": "2026-03-12 05:51:32.000000000",
      "message": "Patch Set 2:\n\nFailed enforced test review-dne-zfs-part-4 on RHEL 8.10 / x86_64 uploaded by Onyx Autotest from onyx-158vm1: https://testing.whamcloud.com/test_sessions/4c916a8e-1d7e-4f64-9ccb-2b02db2f5a9a ran 9 tests.  1 tests failed: sanity-hsm.",
      "accounts_in_message": [],
      "_revision_number": 2
    },
    {
      "id": "c1dbddc0359c003f04a52e542e465e96c971c4b2",
      "author": {
        "_account_id": 147,
        "name": "Maloo",
        "email": "maloo@whamcloud.com",
        "username": "maloo",
        "tags": [
          "SERVICE_USER"
        ]
      },
      "date": "2026-03-12 06:01:30.000000000",
      "message": "Patch Set 2:\n\nFailed enforced test review-dne-zfs-part-2 on RHEL 8.10 / x86_64 uploaded by Onyx Autotest from onyx-152vm3: https://testing.whamcloud.com/test_sessions/202f6177-5ca8-483d-a119-924e41af5388 ran 11 tests.  1 tests failed: sanity-lfsck.",
      "accounts_in_message": [],
      "_revision_number": 2
    },
    {
      "id": "c01c8c83ab714f7da97134f73f14263fd9d65c7a",
      "author": {
        "_account_id": 147,
        "name": "Maloo",
        "email": "maloo@whamcloud.com",
        "username": "maloo",
        "tags": [
          "SERVICE_USER"
        ]
      },
      "date": "2026-03-12 07:08:35.000000000",
      "message": "Patch Set 2:\n\nFailed enforced test review-ldiskfs-ubuntu on RHEL 8.10 / x86_64, Ubuntu 22.04 / x86_64 uploaded by Trevis Autotest from trevis-155vm123: https://testing.whamcloud.com/test_sessions/93108ae2-5ed6-4266-a856-dcb08c352e24 ran 6 tests.  1 tests failed: sanity.",
      "accounts_in_message": [],
      "_revision_number": 2
    },
    {
      "id": "5f664a1b8362aea016c1ba5178230dbdea951dce",
      "author": {
        "_account_id": 147,
        "name": "Maloo",
        "email": "maloo@whamcloud.com",
        "username": "maloo",
        "tags": [
          "SERVICE_USER"
        ]
      },
      "date": "2026-03-12 11:16:12.000000000",
      "message": "Patch Set 2: Verified-1\n\nPassed enforced test review-dne-part-3 on RHEL 9.5 / x86_64 uploaded by Trevis Autotest from trevis-156vm43: https://testing.whamcloud.com/test_sessions/b7a59cb1-3cfd-47c9-a3a2-101bd7ee52db ran 3 tests.",
      "accounts_in_message": [],
      "_revision_number": 2
    },
    {
      "id": "9e9aaab9f6e5a5e1a72e6eb76e71c63e9777f6c4",
      "author": {
        "_account_id": 403,
        "name": "Autotest",
        "email": "autotest@whamcloud.com",
        "username": "autotest",
        "tags": [
          "SERVICE_USER"
        ]
      },
      "date": "2026-03-12 15:05:27.000000000",
      "message": "Patch Set 2:\n\nTrevis Autotest retesting enforced review-dne-zfs-part-4 session on el8.10-x86_64/zfs servers and clients for build 122352 patch 2. Requested by James Simmons because of LU-16932.",
      "accounts_in_message": [],
      "_revision_number": 2
    },
    {
      "id": "b3a17441ca43153d8b220e127b5b0772f6777424",
      "author": {
        "_account_id": 403,
        "name": "Autotest",
        "email": "autotest@whamcloud.com",
        "username": "autotest",
        "tags": [
          "SERVICE_USER"
        ]
      },
      "date": "2026-03-12 15:05:30.000000000",
      "message": "Patch Set 2:\n\nOnyx Autotest retesting enforced review-dne-part-5 session on el8.10-x86_64/ldiskfs servers and clients for build 122352 patch 2. Requested by James Simmons because of LU-12869.",
      "accounts_in_message": [],
      "_revision_number": 2
    },
    {
      "id": "8e53967680dfb9083a57bae5ae3f2541d190bf1c",
      "author": {
        "_account_id": 403,
        "name": "Autotest",
        "email": "autotest@whamcloud.com",
        "username": "autotest",
        "tags": [
          "SERVICE_USER"
        ]
      },
      "date": "2026-03-12 15:05:40.000000000",
      "message": "Patch Set 2:\n\nOnyx Autotest retesting enforced review-dne-zfs-part-2 session on el8.10-x86_64/zfs servers and clients for build 122352 patch 2. Requested by James Simmons because of LU-19747.",
      "accounts_in_message": [],
      "_revision_number": 2
    },
    {
      "id": "2f99aba24a528be428c05dc16a25dfe2704e03bd",
      "author": {
        "_account_id": 403,
        "name": "Autotest",
        "email": "autotest@whamcloud.com",
        "username": "autotest",
        "tags": [
          "SERVICE_USER"
        ]
      },
      "date": "2026-03-12 15:05:48.000000000",
      "message": "Patch Set 2:\n\nTrevis Autotest retesting enforced review-ldiskfs-ubuntu session on el8.10-x86_64/ldiskfs servers and ubuntu2204-x86_64/ldiskfs clients for build 122352 patch 2. Requested by James Simmons because of LU-17856.",
      "accounts_in_message": [],
      "_revision_number": 2
    },
    {
      "id": "1b6ad9b2c53f0d2d494255a0e8b1ca80db3974d4",
      "author": {
        "_account_id": 147,
        "name": "Maloo",
        "email": "maloo@whamcloud.com",
        "username": "maloo",
        "tags": [
          "SERVICE_USER"
        ]
      },
      "date": "2026-03-12 19:24:18.000000000",
      "message": "Patch Set 2:\n\nPassed enforced test review-dne-part-5 on RHEL 8.10 / x86_64 uploaded by Onyx Autotest from onyx-156vm1: https://testing.whamcloud.com/test_sessions/40605f47-88c3-4229-9c72-df7f734d170b ran 5 tests.",
      "accounts_in_message": [],
      "_revision_number": 2
    },
    {
      "id": "62b9ef48cba117efa1b6d6088eda719e3c4a1192",
      "author": {
        "_account_id": 147,
        "name": "Maloo",
        "email": "maloo@whamcloud.com",
        "username": "maloo",
        "tags": [
          "SERVICE_USER"
        ]
      },
      "date": "2026-03-12 19:42:41.000000000",
      "message": "Patch Set 2:\n\nPassed enforced test review-dne-zfs-part-2 on RHEL 8.10 / x86_64 uploaded by Onyx Autotest from onyx-156vm44: https://testing.whamcloud.com/test_sessions/fbeadcf7-39f6-4daa-ba36-bdab50aaeaee ran 11 tests.",
      "accounts_in_message": [],
      "_revision_number": 2
    },
    {
      "id": "a829c64e34cfa98d2331dc9b6508d2847c7ebc00",
      "author": {
        "_account_id": 147,
        "name": "Maloo",
        "email": "maloo@whamcloud.com",
        "username": "maloo",
        "tags": [
          "SERVICE_USER"
        ]
      },
      "date": "2026-03-12 19:44:38.000000000",
      "message": "Patch Set 2:\n\nPassed enforced test review-dne-zfs-part-4 on RHEL 8.10 / x86_64 uploaded by Trevis Autotest from trevis-156vm45: https://testing.whamcloud.com/test_sessions/744ea331-bfac-490e-84fa-3d905dd7268e ran 9 tests.",
      "accounts_in_message": [],
      "_revision_number": 2
    },
    {
      "id": "a75090d9a4f3f5dcccf6657f2b61cb9b825d2b3b",
      "author": {
        "_account_id": 147,
        "name": "Maloo",
        "email": "maloo@whamcloud.com",
        "username": "maloo",
        "tags": [
          "SERVICE_USER"
        ]
      },
      "date": "2026-03-12 20:44:21.000000000",
      "message": "Patch Set 2: Verified+1\n\nPassed enforced test review-ldiskfs-ubuntu on RHEL 8.10 / x86_64, Ubuntu 22.04 / x86_64 uploaded by Trevis Autotest from trevis-153vm25: https://testing.whamcloud.com/test_sessions/0302e9d6-303c-44f3-b2f5-e46e018845e9 ran 6 tests.",
      "accounts_in_message": [],
      "_revision_number": 2
    },
    {
      "id": "7ffc02528843bea2fda7e8a567c36b2fbff6e899",
      "tag": "autogenerated:gerrit:setTopic",
      "author": {
        "_account_id": 125,
        "name": "James Simmons",
        "email": "jsimmons@infradead.org",
        "username": "jsimmons"
      },
      "date": "2026-03-13 00:19:30.000000000",
      "message": "Topic set to upstream",
      "accounts_in_message": [],
      "_revision_number": 2
    },
    {
      "id": "9ce680ac5ea3e3993fc5277b5ae1d88524092eec",
      "author": {
        "_account_id": 931,
        "name": "Timothy Day",
        "email": "timday@thelustrecollective.com",
        "username": "timday"
      },
      "date": "2026-03-14 02:19:21.000000000",
      "message": "Patch Set 2: Code-Review+1",
      "accounts_in_message": [],
      "_revision_number": 2
    },
    {
      "id": "61eb94a0dbf52cd5db3256674e56d1b588492792",
      "author": {
        "_account_id": 117,
        "name": "Andreas Dilger",
        "email": "adilger@thelustrecollective.com",
        "username": "adilger"
      },
      "date": "2026-03-14 09:40:10.000000000",
      "message": "Patch Set 2: Code-Review+1",
      "accounts_in_message": [],
      "_revision_number": 2
    },
    {
      "id": "3d60f98465057e5b45873a43451be748fb7489eb",
      "author": {
        "_account_id": 112,
        "name": "Oleg Drokin",
        "email": "green@whamcloud.com",
        "username": "green"
      },
      "date": "2026-03-30 01:57:41.000000000",
      "message": "Patch Set 2:\n\n(2 comments)",
      "accounts_in_message": [],
      "_revision_number": 2
    },
    {
      "id": "367aa5493daf021c7db08fd69b5965edf8a94aa9",
      "author": {
        "_account_id": 125,
        "name": "James Simmons",
        "email": "jsimmons@infradead.org",
        "username": "jsimmons"
      },
      "date": "2026-03-31 00:42:45.000000000",
      "message": "Patch Set 2:\n\n(2 comments)",
      "accounts_in_message": [],
      "_revision_number": 2
    },
    {
      "id": "5a3f274ccc8136c871de0c2b6d11a9f8ddf6e93f",
      "author": {
        "_account_id": 112,
        "name": "Oleg Drokin",
        "email": "green@whamcloud.com",
        "username": "green"
      },
      "date": "2026-03-31 05:32:19.000000000",
      "message": "Patch Set 2: Code-Review+2",
      "accounts_in_message": [],
      "_revision_number": 2
    },
    {
      "id": "6647f251384623e2045d1769e5d15b088081356d",
      "tag": "autogenerated:gerrit:merged",
      "author": {
        "_account_id": 112,
        "name": "Oleg Drokin",
        "email": "green@whamcloud.com",
        "username": "green"
      },
      "date": "2026-03-31 05:32:22.000000000",
      "message": "Change has been successfully cherry-picked as c981360d6e7edb96a856e73e16319c0360fe237f",
      "accounts_in_message": [],
      "_revision_number": 3
    },
    {
      "id": "3ac8822a91285a5fa35f99a9a7d0539565b50a78",
      "author": {
        "_account_id": 125,
        "name": "James Simmons",
        "email": "jsimmons@infradead.org",
        "username": "jsimmons"
      },
      "date": "2026-03-31 17:17:22.000000000",
      "message": "Patch Set 3:\n\n(2 comments)",
      "accounts_in_message": [],
      "_revision_number": 3
    }
  ],
  "current_revision_number": 3,
  "current_revision": "c981360d6e7edb96a856e73e16319c0360fe237f",
  "revisions": {
    "c981360d6e7edb96a856e73e16319c0360fe237f": {
      "kind": "TRIVIAL_REBASE_WITH_MESSAGE_UPDATE",
      "_number": 3,
      "created": "2026-03-31 05:32:22.000000000",
      "uploader": {
        "_account_id": 112,
        "name": "Oleg Drokin",
        "email": "green@whamcloud.com",
        "username": "green"
      },
      "ref": "refs/changes/11/64511/3",
      "fetch": {
        "anonymous http": {
          "url": "https://review.whamcloud.com/fs/lustre-release",
          "ref": "refs/changes/11/64511/3"
        }
      },
      "commit": {
        "parents": [
          {
            "commit": "dc808d3dfe4ca7218cca44ad6e10a50df3f0f29a",
            "subject": "LU-19179 lustre: remove support for kernels 4.0 to 4.5"
          }
        ],
        "author": {
          "name": "James Simmons",
          "email": "jsimmons@infradead.org",
          "date": "2026-03-11 23:05:05.000000000",
          "tz": -240
        },
        "committer": {
          "name": "Oleg Drokin",
          "email": "green@whamcloud.com",
          "date": "2026-03-31 05:32:22.000000000",
          "tz": 0
        },
        "subject": "LU-19179 lustre: remove remaining 4.X kernel support",
        "message": "LU-19179 lustre: remove remaining 4.X kernel support\n\nAll kernels before 5.0 are no longer supported so cleanup the\ncode.\n\nSigned-off-by: James Simmons <jsimmons@infradead.org>\nChange-Id: I1da27481bd609ba93ca4736a9bddb6a58e6e6371\nReviewed-on: https://review.whamcloud.com/c/fs/lustre-release/+/64511\nTested-by: jenkins <devops@whamcloud.com>\nReviewed-by: Oleg Drokin <green@whamcloud.com>\nReviewed-by: Andreas Dilger <adilger@thelustrecollective.com>\nTested-by: Maloo <maloo@whamcloud.com>\nReviewed-by: Timothy Day <timday@thelustrecollective.com>\n"
      },
      "branch": "refs/heads/master"
    }
  },
  "requirements": [],
  "submit_records": [
    {
      "rule_name": "gerrit~DefaultSubmitRule",
      "status": "CLOSED",
      "labels": [
        {
          "label": "Verified",
          "status": "OK",
          "applied_by": {
            "_account_id": 147,
            "name": "Maloo",
            "email": "maloo@whamcloud.com",
            "username": "maloo",
            "tags": [
              "SERVICE_USER"
            ]
          }
        },
        {
          "label": "Code-Review",
          "status": "OK",
          "applied_by": {
            "_account_id": 112,
            "name": "Oleg Drokin",
            "email": "green@whamcloud.com",
            "username": "green"
          }
        }
      ]
    }
  ]
}