<?xml version='1.0' encoding='utf-8'?>
<mediawiki xmlns:ns1="http://www.mediawiki.org/xml/export-0.11/" xmlns:xsi="http://www.w3.org/2001/XMLSchema-instance" xsi:schemaLocation="http://www.mediawiki.org/xml/export-0.11/ http://www.mediawiki.org/xml/export-0.11.xsd" version="0.11" xml:lang="en">
  <ns1:siteinfo>
    <ns1:sitename>Lustre Wiki</ns1:sitename>
    <ns1:dbname>wiki_lustre_org</ns1:dbname>
    <ns1:base>http://wiki.lustre.org/Main_Page</ns1:base>
    <ns1:generator>MediaWiki 1.39.7</ns1:generator>
    <ns1:case>first-letter</ns1:case>
    <ns1:namespaces>
      <ns1:namespace key="-2" case="first-letter">Media</ns1:namespace>
      <ns1:namespace key="-1" case="first-letter">Special</ns1:namespace>
      <ns1:namespace key="0" case="first-letter" />
      <ns1:namespace key="1" case="first-letter">Talk</ns1:namespace>
      <ns1:namespace key="2" case="first-letter">User</ns1:namespace>
      <ns1:namespace key="3" case="first-letter">User talk</ns1:namespace>
      <ns1:namespace key="4" case="first-letter">Lustre Wiki</ns1:namespace>
      <ns1:namespace key="5" case="first-letter">Lustre Wiki talk</ns1:namespace>
      <ns1:namespace key="6" case="first-letter">File</ns1:namespace>
      <ns1:namespace key="7" case="first-letter">File talk</ns1:namespace>
      <ns1:namespace key="8" case="first-letter">MediaWiki</ns1:namespace>
      <ns1:namespace key="9" case="first-letter">MediaWiki talk</ns1:namespace>
      <ns1:namespace key="10" case="first-letter">Template</ns1:namespace>
      <ns1:namespace key="11" case="first-letter">Template talk</ns1:namespace>
      <ns1:namespace key="12" case="first-letter">Help</ns1:namespace>
      <ns1:namespace key="13" case="first-letter">Help talk</ns1:namespace>
      <ns1:namespace key="14" case="first-letter">Category</ns1:namespace>
      <ns1:namespace key="15" case="first-letter">Category talk</ns1:namespace>
    </ns1:namespaces>
  </ns1:siteinfo>
  <ns1:page>
    <ns1:title>Lustre 2.13.0 Changelog</ns1:title>
    <ns1:ns>0</ns1:ns>
    <ns1:id>1523</ns1:id>
    <ns1:revision>
      <ns1:id>4946</ns1:id>
      <ns1:parentid>3725</ns1:parentid>
      <ns1:timestamp>2024-10-07T13:46:40Z</ns1:timestamp>
      <ns1:contributor>
        <ns1:username>Elliswilson</ns1:username>
        <ns1:id>140</ns1:id>
      </ns1:contributor>
      <ns1:minor />
      <ns1:origin>4946</ns1:origin>
      <ns1:model>wikitext</ns1:model>
      <ns1:format>text/x-wiki</ns1:format>
      <ns1:text bytes="62245" sha1="l208nxqejsy0ggdorjjcezf5bnlt0dt" xml:space="preserve">'''Server support for kernels: '''&lt;br /&gt;
*RHEL 7.7 (3.10.0-1062.1.1.el7)

'''Client support for unpatched kernels: '''&lt;br /&gt;
*RHEL 7.7 (3.10.0-1062.1.1.el7)
*SLES12 SP4 (4.12.14-95.29.1)
*Ubuntu 18.04 (4.15.0-64)

'''Recommended e2fsprogs version: '''&lt;br /&gt;
*v1.45.2.wc1

'''Interoperability Support: '''&lt;br /&gt;
*Clients &amp; Servers: Latest 2.12.X

== Issues fixed between 2.12.0 and 2.13.0 ==
''' New Feature '''
*[https://jira.whamcloud.com/browse/LU-1365 LU-1365]: Implement ldiskfs LARGEDIR support for e2fsprogs
*[https://jira.whamcloud.com/browse/LU-9846 LU-9846]: Overstriping - more than 1 stripe per OST per component
*[https://jira.whamcloud.com/browse/LU-10070 LU-10070]: PFL self-extending file layout
*[https://jira.whamcloud.com/browse/LU-10092 LU-10092]: PCC: Lustre Persistent Client Cache
*[https://jira.whamcloud.com/browse/LU-11297 LU-11297]: Align LNet routing with Multi-Rail and LNet health
*[https://jira.whamcloud.com/browse/LU-11376 LU-11376]: Special file/dir to represent DAOS Containers
*[https://jira.whamcloud.com/browse/LU-12624 LU-12624]: striped directory allocate stripes by QoS
*[https://jira.whamcloud.com/browse/LU-12734 LU-12734]: bash completion (for now: lctl set/get_param)

''' Improvement '''
*[https://jira.whamcloud.com/browse/LU-1538 LU-1538]: cleanup test scripts
*[https://jira.whamcloud.com/browse/LU-2233 LU-2233]: sanityn/40-46 takes ~800-900s
*[https://jira.whamcloud.com/browse/LU-7004 LU-7004]: fix &amp;quot;lctl set_param -P&amp;quot; to allow deprecation of &amp;quot;lctl conf_param&amp;quot;
*[https://jira.whamcloud.com/browse/LU-8207 LU-8207]: Add auto-stripe option to lfs_migrate
*[https://jira.whamcloud.com/browse/LU-8434 LU-8434]: Rewrite test framework using Python
*[https://jira.whamcloud.com/browse/LU-8939 LU-8939]: nodemap: remove deprecated lproc files
*[https://jira.whamcloud.com/browse/LU-8955 LU-8955]: Send SELinux policy info to server
*[https://jira.whamcloud.com/browse/LU-9010 LU-9010]: use static initialization for statically allocated objects when possible
*[https://jira.whamcloud.com/browse/LU-9625 LU-9625]: remove &amp;quot;lfs ls&amp;quot; and &amp;quot;lfs cp&amp;quot; and references
*[https://jira.whamcloud.com/browse/LU-9629 LU-9629]: lfs migrate does not work as a non-root user
*[https://jira.whamcloud.com/browse/LU-10258 LU-10258]: lfs mirror command to open fd on component
*[https://jira.whamcloud.com/browse/LU-10885 LU-10885]: enable flock by default
*[https://jira.whamcloud.com/browse/LU-11010 LU-11010]: Remove call to ‘return’ after call to ‘skip’ in Lustre test suites
*[https://jira.whamcloud.com/browse/LU-11011 LU-11011]: checksum type can not be selected permanently
*[https://jira.whamcloud.com/browse/LU-11022 LU-11022]: FLR1.5: &amp;quot;lfs mirror&amp;quot; usability for Burst Buffer
*[https://jira.whamcloud.com/browse/LU-11041 LU-11041]: enable build and test with kernel debug options
*[https://jira.whamcloud.com/browse/LU-11078 LU-11078]: customise run_ior()
*[https://jira.whamcloud.com/browse/LU-11089 LU-11089]: Performance improvements for lu_object locking
*[https://jira.whamcloud.com/browse/LU-11213 LU-11213]: DNE3: remote mkdir() in ROOT/ by default
*[https://jira.whamcloud.com/browse/LU-11221 LU-11221]: Do not hold pages locked for network IO on the server.
*[https://jira.whamcloud.com/browse/LU-11233 LU-11233]: gcc8 support
*[https://jira.whamcloud.com/browse/LU-11285 LU-11285]: don't stop on the first blocked lock in ldlm_reprocess_queue()
*[https://jira.whamcloud.com/browse/LU-11296 LU-11296]: page cache cleanup improvement on lock flush
*[https://jira.whamcloud.com/browse/LU-11329 LU-11329]: add get_maintainer.pl script from kernel
*[https://jira.whamcloud.com/browse/LU-11355 LU-11355]: Add Lustre trim support
*[https://jira.whamcloud.com/browse/LU-11367 LU-11367]: integrate LSOM with lfs find
*[https://jira.whamcloud.com/browse/LU-11398 LU-11398]: clean up ptlrpc completion callbacks
*[https://jira.whamcloud.com/browse/LU-11408 LU-11408]: propagate grant shrink interval immediately
*[https://jira.whamcloud.com/browse/LU-11415 LU-11415]: ksocklnd performance improvement on 40Gbps ethernet
*[https://jira.whamcloud.com/browse/LU-11456 LU-11456]: MDT can skip sync if the object is synced yet
*[https://jira.whamcloud.com/browse/LU-11462 LU-11462]: osd-zfs can skip object sync if it's not dirty
*[https://jira.whamcloud.com/browse/LU-11467 LU-11467]: FLR1.5: add &amp;quot;lfs mirror delete&amp;quot; command
*[https://jira.whamcloud.com/browse/LU-11504 LU-11504]: improve ha.sh to trigger lfsck after/during failover/failback
*[https://jira.whamcloud.com/browse/LU-11526 LU-11526]: Support 64MB I/O RPC
*[https://jira.whamcloud.com/browse/LU-11555 LU-11555]: warn when mounting ZFS pools without &amp;quot;multihost&amp;quot; enabled
*[https://jira.whamcloud.com/browse/LU-11606 LU-11606]: use llapi_error() for errors in liblustreapi files
*[https://jira.whamcloud.com/browse/LU-11616 LU-11616]: Optimize handling statahead delay
*[https://jira.whamcloud.com/browse/LU-11673 LU-11673]: Correct shell issues/mistakes in Lustre test suites
*[https://jira.whamcloud.com/browse/LU-11717 LU-11717]: t-f:exit_status () defect: test returns code 1 if log contains &amp;quot;FAIL&amp;quot;
*[https://jira.whamcloud.com/browse/LU-11736 LU-11736]: Do not apply bulk IO tuning on MDT or MGT devices
*[https://jira.whamcloud.com/browse/LU-11739 LU-11739]: Don't inherit default layout from root for new subdirectories
*[https://jira.whamcloud.com/browse/LU-11810 LU-11810]: allow &amp;quot;Fixes:&amp;quot; tag in commit message signoff block
*[https://jira.whamcloud.com/browse/LU-11811 LU-11811]: Provide an interface to set Lustre MDT into readonly mode
*[https://jira.whamcloud.com/browse/LU-11820 LU-11820]: reduce conf-sanity test duration
*[https://jira.whamcloud.com/browse/LU-11830 LU-11830]: Quiet compiler warnings on ARM
*[https://jira.whamcloud.com/browse/LU-11834 LU-11834]: config instance truncation due to buffer size mismatch
*[https://jira.whamcloud.com/browse/LU-11838 LU-11838]: Support linux kernel version 4.18
*[https://jira.whamcloud.com/browse/LU-11843 LU-11843]: customise sanity-quota to work with project quotas set before the suite
*[https://jira.whamcloud.com/browse/LU-11845 LU-11845]: Support encrypted ZFS volumes
*[https://jira.whamcloud.com/browse/LU-11852 LU-11852]: osc cache waiters wakeups and skipping queue
*[https://jira.whamcloud.com/browse/LU-11876 LU-11876]: Lustre dkms packages missing build dependency
*[https://jira.whamcloud.com/browse/LU-11885 LU-11885]: reset quota setting upon test failed
*[https://jira.whamcloud.com/browse/LU-11902 LU-11902]: Remove obsolete lustre-utils files and entries for DEB packages
*[https://jira.whamcloud.com/browse/LU-11913 LU-11913]: mq-deadline should be in the list of allowed schedulers
*[https://jira.whamcloud.com/browse/LU-11914 LU-11914]: Build error for l_getsepol.c due to missing openssl/evp.h
*[https://jira.whamcloud.com/browse/LU-11923 LU-11923]: meta_bg conflicts with resize_inode if explicitly specified for a small filesystem
*[https://jira.whamcloud.com/browse/LU-11924 LU-11924]: Combine cancellation of llog records at osp_sync_process_committed
*[https://jira.whamcloud.com/browse/LU-11963 LU-11963]: Add nonrotational flag to obd_statfs
*[https://jira.whamcloud.com/browse/LU-11974 LU-11974]: Improve llapi_layout_get_by_xattr()
*[https://jira.whamcloud.com/browse/LU-11982 LU-11982]: Incorrect text in lfs migrate help
*[https://jira.whamcloud.com/browse/LU-11999 LU-11999]: DNE performance improvement
*[https://jira.whamcloud.com/browse/LU-12015 LU-12015]: Update Changelog for ubuntu kernel version
*[https://jira.whamcloud.com/browse/LU-12019 LU-12019]: Recognize Debian Kernel in autoconf and unify kernel module package directory
*[https://jira.whamcloud.com/browse/LU-12027 LU-12027]: Allow &amp;quot;lfs find&amp;quot; atime/mtime/ctime with fine-grained values
*[https://jira.whamcloud.com/browse/LU-12033 LU-12033]: Git ignore generated *.install server and client files
*[https://jira.whamcloud.com/browse/LU-12044 LU-12044]: Translate HABEO_ macros to English
*[https://jira.whamcloud.com/browse/LU-12045 LU-12045]: Ability to split test script execution into parts
*[https://jira.whamcloud.com/browse/LU-12090 LU-12090]: Create an lfs command to remove files by FID
*[https://jira.whamcloud.com/browse/LU-12093 LU-12093]: CAP_SYS_RESOURCE capability check overhead
*[https://jira.whamcloud.com/browse/LU-12103 LU-12103]: Improve block allocation for large partitions
*[https://jira.whamcloud.com/browse/LU-12133 LU-12133]: sanityn test_35() defect
*[https://jira.whamcloud.com/browse/LU-12137 LU-12137]: update client to use iterate_shared
*[https://jira.whamcloud.com/browse/LU-12157 LU-12157]: lfs_migrate -v output format is not well-formed
*[https://jira.whamcloud.com/browse/LU-12159 LU-12159]: allow lfs getname to only print fsname
*[https://jira.whamcloud.com/browse/LU-12202 LU-12202]: remove obsolete files from contrib
*[https://jira.whamcloud.com/browse/LU-12226 LU-12226]: upgrade e2fsprogs to 1.45.2
*[https://jira.whamcloud.com/browse/LU-12236 LU-12236]: Support more than the default root network namespace
*[https://jira.whamcloud.com/browse/LU-12270 LU-12270]: Support linux kernel version 4.19
*[https://jira.whamcloud.com/browse/LU-12302 LU-12302]: 0@lo status shows as &amp;quot;down&amp;quot;
*[https://jira.whamcloud.com/browse/LU-12313 LU-12313]: Mark lustre_inode_cache as reclaimable
*[https://jira.whamcloud.com/browse/LU-12326 LU-12326]: test-framework to recognize Bochs as VM
*[https://jira.whamcloud.com/browse/LU-12330 LU-12330]: Support per-session JOBID without using the environment
*[https://jira.whamcloud.com/browse/LU-12331 LU-12331]: hardened usercopy whitelisting
*[https://jira.whamcloud.com/browse/LU-12333 LU-12333]: Add additional rpc flags to DEBUG_REQ_FLAGS
*[https://jira.whamcloud.com/browse/LU-12341 LU-12341]: Make test-framework aware of kmemleak
*[https://jira.whamcloud.com/browse/LU-12349 LU-12349]: print error to console when flock() is diabled
*[https://jira.whamcloud.com/browse/LU-12368 LU-12368]: concurrent statfs() calls on the client should be blocked
*[https://jira.whamcloud.com/browse/LU-12430 LU-12430]: remove misleading help message of &amp;quot;Consult build/README.kernel-source for details&amp;quot;
*[https://jira.whamcloud.com/browse/LU-12439 LU-12439]: Convert &amp;quot;Response timed out...&amp;quot; in lnet_finalize_expired_responses to CDEBUG
*[https://jira.whamcloud.com/browse/LU-12440 LU-12440]: Correct lnet_is_health_check when msg status is 0
*[https://jira.whamcloud.com/browse/LU-12492 LU-12492]: Deprecate live/dead router check interval parameters (instead of removing them)
*[https://jira.whamcloud.com/browse/LU-12509 LU-12509]: lockdep warning in ofd_precreate_objects()
*[https://jira.whamcloud.com/browse/LU-12516 LU-12516]: volatile file creation in .lustre/fid/
*[https://jira.whamcloud.com/browse/LU-12520 LU-12520]: reserve lru pages for read in batch
*[https://jira.whamcloud.com/browse/LU-12527 LU-12527]: lustreapi.h not c++ compatible
*[https://jira.whamcloud.com/browse/LU-12533 LU-12533]: Improve readahead RPC issuance for large window sizes
*[https://jira.whamcloud.com/browse/LU-12535 LU-12535]: lov_page_index surprisingly slow
*[https://jira.whamcloud.com/browse/LU-12545 LU-12545]: Cleanup LPROC_LL_*
*[https://jira.whamcloud.com/browse/LU-12553 LU-12553]: polling mode for changelog driver
*[https://jira.whamcloud.com/browse/LU-12562 LU-12562]: sanity 256 to use /tmp for temporary file
*[https://jira.whamcloud.com/browse/LU-12578 LU-12578]: obdfilter-survey w/echo-client does not gain from direct-io optimizations
*[https://jira.whamcloud.com/browse/LU-12621 LU-12621]: o2iblnd QP sizing -EINVAL retries
*[https://jira.whamcloud.com/browse/LU-12635 LU-12635]: gcc: -Werror=implicit-fallthrough
*[https://jira.whamcloud.com/browse/LU-12776 LU-12776]: update lustre/ChangeLog to reflect primary kernels
*[https://jira.whamcloud.com/browse/LU-12789 LU-12789]: Mellanox MOFED 4.7 support.
*[https://jira.whamcloud.com/browse/LU-12802 LU-12802]: racer test stucks after test finishes
*[https://jira.whamcloud.com/browse/LU-12825 LU-12825]: Build MOFED 4.7
*[https://jira.whamcloud.com/browse/LU-12845 LU-12845]: Fix typos in ‘lctl pcc’ help message

''' Bug '''
*[https://jira.whamcloud.com/browse/LU-1732 LU-1732]: enable wide striping by default
*[https://jira.whamcloud.com/browse/LU-1957 LU-1957]: Test failure on test suite sanity, subtest test_180b
*[https://jira.whamcloud.com/browse/LU-4322 LU-4322]: sanity test_101a: too many discarded pages
*[https://jira.whamcloud.com/browse/LU-4398 LU-4398]: mdt_object_open_lock() may not flush conflicting handles
*[https://jira.whamcloud.com/browse/LU-5604 LU-5604]: Lots of FAIL_ID checking are lost
*[https://jira.whamcloud.com/browse/LU-6504 LU-6504]: Wrong indentation in socklnd
*[https://jira.whamcloud.com/browse/LU-6836 LU-6836]: sanity-quota test_4a: Passed grace time 12, 1436542665, 1436542679
*[https://jira.whamcloud.com/browse/LU-6951 LU-6951]: sanity test_27m: @@@@@@ FAIL: OST0 was full but new created file still use it
*[https://jira.whamcloud.com/browse/LU-7159 LU-7159]: sanity 224c always passes
*[https://jira.whamcloud.com/browse/LU-7239 LU-7239]: mdd_attr_set() synchronous when it need not be
*[https://jira.whamcloud.com/browse/LU-7558 LU-7558]: niobuf.c:721:ptl_send_rpc() LASSERT(AT_OFF || imp_state != LUSTRE_IMP_FULL || imp_msghdr_flags &amp;amp; MSGHDR_AT_SUPPORT ...)
*[https://jira.whamcloud.com/browse/LU-7631 LU-7631]: conf-sanity test_82a: getstripe -c wrong: found 2, expected 3
*[https://jira.whamcloud.com/browse/LU-7912 LU-7912]: Stale comment in osc_page_transfer_add
*[https://jira.whamcloud.com/browse/LU-8047 LU-8047]: optimize ll_md_blocking_ast() for a failed lock
*[https://jira.whamcloud.com/browse/LU-8260 LU-8260]: osd_ldiskfs fiemap code wrong address space usage
*[https://jira.whamcloud.com/browse/LU-8299 LU-8299]: (vvp_io.c:922:vvp_io_fault_start()) ASSERTION( cl_index(obj, offset) == fio-&amp;gt;ft_index )
*[https://jira.whamcloud.com/browse/LU-8760 LU-8760]: sanity-lfsck test 31g hung
*[https://jira.whamcloud.com/browse/LU-9193 LU-9193]: Multiple hangs observed with many open/getattr
*[https://jira.whamcloud.com/browse/LU-9341 LU-9341]: PFL: append should not instantiate full layout
*[https://jira.whamcloud.com/browse/LU-9706 LU-9706]: conf-sanity test_53a: MDS soft lockup - CPU#0 stuck for 22s in osd_trans_commit_cb()
*[https://jira.whamcloud.com/browse/LU-9792 LU-9792]: &amp;quot;loop&amp;quot; devices testing with zfs is broken
*[https://jira.whamcloud.com/browse/LU-9835 LU-9835]: Potential buffer overrun in jt_opt_threads()
*[https://jira.whamcloud.com/browse/LU-9862 LU-9862]: The patch that landed for LU-7890 leads to static checker errors
*[https://jira.whamcloud.com/browse/LU-9920 LU-9920]: Use pagevec for marking pages dirty
*[https://jira.whamcloud.com/browse/LU-9964 LU-9964]: &amp;gt; 1 group lock on same file (group lock lifecycle/cbpending problem)
*[https://jira.whamcloud.com/browse/LU-9971 LU-9971]: MR: ABA problem in lnet_discover_peer_locked
*[https://jira.whamcloud.com/browse/LU-10048 LU-10048]: osd-ldiskfs to truncate outside of main transaction
*[https://jira.whamcloud.com/browse/LU-10094 LU-10094]: sanity test_17f: 'ls' fails with &amp;quot;ls: reading directory *: Input/output error&amp;quot;
*[https://jira.whamcloud.com/browse/LU-10100 LU-10100]: sanity test_27a: setstripe failed with &amp;quot;error on ioctl 0x8008669a for '*' (3): Invalid argument&amp;quot;
*[https://jira.whamcloud.com/browse/LU-10153 LU-10153]: route via two different networks not supported
*[https://jira.whamcloud.com/browse/LU-10239 LU-10239]: Lustre crash (client): The first extent to be fit in a RPC contains 17 chunks, which is over the limit 16.
*[https://jira.whamcloud.com/browse/LU-10384 LU-10384]: Replace nids doesn't add failover nid and add_conn string to config
*[https://jira.whamcloud.com/browse/LU-10496 LU-10496]: sanity-dom sanity test_39k: FAIL: mtime is lost on close: 1515705427, should be 1484169395
*[https://jira.whamcloud.com/browse/LU-10717 LU-10717]: several conf-sanity tests failed: FAIL: start mgs failed
*[https://jira.whamcloud.com/browse/LU-10754 LU-10754]: sanityn test 47b fails with 'create must fail'
*[https://jira.whamcloud.com/browse/LU-10815 LU-10815]: sanity-scrub test_16: @@@@@@ FAIL: test_16 failed with 2
*[https://jira.whamcloud.com/browse/LU-10862 LU-10862]: ldlm_pools_{count,shrink}() DLMTRACE it too noisy
*[https://jira.whamcloud.com/browse/LU-10866 LU-10866]: Add mount options for pacemaker script
*[https://jira.whamcloud.com/browse/LU-10883 LU-10883]: llog backup files processing is not skipped because of string сomparison error
*[https://jira.whamcloud.com/browse/LU-10913 LU-10913]: conf-sanity test_106: OST0000-osc-MDT0000: can't cancel record
*[https://jira.whamcloud.com/browse/LU-10929 LU-10929]: skip sanity/315 if IO accounting is not supported
*[https://jira.whamcloud.com/browse/LU-10931 LU-10931]: failed peer discovery still taking too long
*[https://jira.whamcloud.com/browse/LU-10949 LU-10949]: LBUG lu_object.h:688:lu_object_get()) ASSERTION( atomic_read(&amp;amp;o-&amp;gt;lo_header-&amp;gt;loh_ref) &amp;gt; 0 ) failed
*[https://jira.whamcloud.com/browse/LU-10953 LU-10953]: sanity/300k fails on local small setups
*[https://jira.whamcloud.com/browse/LU-10966 LU-10966]: `lfs check` documentation is misleading
*[https://jira.whamcloud.com/browse/LU-11090 LU-11090]: sanity-lfsck test_4 failed: Oops: 0000 [#1] IP: qsd_config 0x110/0x350 [lquota]
*[https://jira.whamcloud.com/browse/LU-11111 LU-11111]: crash doing LFSCK: orph_index_insert()) ASSERTION( !(obj-&amp;gt;mod_flags &amp;amp; ORPHAN_OBJ)
*[https://jira.whamcloud.com/browse/LU-11157 LU-11157]: sanity test_42e: invalid arithmetic operator (error token is &amp;quot;.9&amp;quot;)
*[https://jira.whamcloud.com/browse/LU-11161 LU-11161]: sanity test_160g fails for DNE with ''mds2: User cl9 still registered''
*[https://jira.whamcloud.com/browse/LU-11204 LU-11204]: mdt_reint_unlink-&amp;gt;lu_object_put() crash
*[https://jira.whamcloud.com/browse/LU-11206 LU-11206]: recovery-mds-scale test failover_ost fails with 'import is not in FULL state'
*[https://jira.whamcloud.com/browse/LU-11208 LU-11208]: Interop 2.10.4&amp;lt;-&amp;gt;master sanity test_27G: 'testpool' is not empty
*[https://jira.whamcloud.com/browse/LU-11239 LU-11239]: sanity-lfsck test 36a fails with 'Fail to split mirror'
*[https://jira.whamcloud.com/browse/LU-11243 LU-11243]: Assertion and hang upon lod_add_device failure
*[https://jira.whamcloud.com/browse/LU-11251 LU-11251]: replay-single test_70b test: ASSERTION( req_transno &amp;lt; next_transno ) failed: LBUG
*[https://jira.whamcloud.com/browse/LU-11292 LU-11292]: LNet: Run discovery protocols on routers
*[https://jira.whamcloud.com/browse/LU-11330 LU-11330]: replay-single test_70d: Directory not empty rmdir fails
*[https://jira.whamcloud.com/browse/LU-11359 LU-11359]: racer test 1 times out with client hung in dir_create.sh, ls, … and MDS in ldlm_completion_ast()
*[https://jira.whamcloud.com/browse/LU-11401 LU-11401]: Interop: sanity-flr test 203 needs server version check
*[https://jira.whamcloud.com/browse/LU-11402 LU-11402]: Interop: sanity-quota test 60 needs a server version check
*[https://jira.whamcloud.com/browse/LU-11403 LU-11403]: lov_io_init_empty() Page fault on a file without stripes
*[https://jira.whamcloud.com/browse/LU-11409 LU-11409]: only first 100 OSC can shrink grants
*[https://jira.whamcloud.com/browse/LU-11413 LU-11413]: Large performance degradation in routing environment.
*[https://jira.whamcloud.com/browse/LU-11418 LU-11418]: hung threads on MDT and MDT won't umount
*[https://jira.whamcloud.com/browse/LU-11426 LU-11426]: 2/2 Olafs agree: changelog entries are emitted out of order
*[https://jira.whamcloud.com/browse/LU-11434 LU-11434]: Interop 2.10.5&amp;lt;-&amp;gt;master conf-sanity test_109a: clear_conf failed
*[https://jira.whamcloud.com/browse/LU-11444 LU-11444]: RPC resend may corrupt the data
*[https://jira.whamcloud.com/browse/LU-11453 LU-11453]: sanity test 184a: Basic layout swap panics on Power8
*[https://jira.whamcloud.com/browse/LU-11485 LU-11485]: MDS allows &amp;quot;lfs setstripe&amp;quot; to mark last mirror as stale
*[https://jira.whamcloud.com/browse/LU-11495 LU-11495]: t-f defect: NAME=ncli llmount failed with FILESET set
*[https://jira.whamcloud.com/browse/LU-11496 LU-11496]: recovery scale tests with IOR load are not functional
*[https://jira.whamcloud.com/browse/LU-11503 LU-11503]: ha.sh defects: ha.sh: line 399: (1476438773 - start_time) / nr_loops: division by 0
*[https://jira.whamcloud.com/browse/LU-11537 LU-11537]: Fix assertion: osd_trans_exec_op()) ASSERTION( !ldiskfs_track_declares_assert )
*[https://jira.whamcloud.com/browse/LU-11542 LU-11542]: Race between imp_state and imp_invalid
*[https://jira.whamcloud.com/browse/LU-11549 LU-11549]: Unattached inodes after 3 min racer run.
*[https://jira.whamcloud.com/browse/LU-11566 LU-11566]: sanity test_60aa: llog_print_cb()) not enough space for print log records
*[https://jira.whamcloud.com/browse/LU-11568 LU-11568]: Get rid of SLAB_DESTROY_BY_RCU
*[https://jira.whamcloud.com/browse/LU-11575 LU-11575]: make debs fail on debian without systemd enabled
*[https://jira.whamcloud.com/browse/LU-11579 LU-11579]: cl_file_inode_init()) ASSERTION(inode-&amp;gt;i_state &amp;amp; (1 &amp;lt;&amp;lt; 3) ) failed:
*[https://jira.whamcloud.com/browse/LU-11584 LU-11584]: kernel BUG at ldiskfs.h:1907!
*[https://jira.whamcloud.com/browse/LU-11585 LU-11585]: recovery-double-scale test_pairwise_fail: Oops: BUG: unable to handle kernel NULL pointer dereference: qsd_lqe_read+0x284/0x570 [lquota]
*[https://jira.whamcloud.com/browse/LU-11586 LU-11586]: sanity-pfl test_10: FAIL: /mnt/lustre/d10.sanity-pfl/file2 does not inherite root layout (subdiretory mounts)
*[https://jira.whamcloud.com/browse/LU-11591 LU-11591]: MDS n003 crash, LustreError: 20558:0:(osp_sync.c:1258:osp_sync_thread()) ASSERTION( thread-&amp;gt;t_flags != SVC_RUNNING ) failed: 4632 changes, 16403 in progress, 0 in flight
*[https://jira.whamcloud.com/browse/LU-11594 LU-11594]: sanity test_103a: FAIL: permissions failed
*[https://jira.whamcloud.com/browse/LU-11601 LU-11601]: IR doesn't handle EAGAIN after initial connect when pinger_recov is 0
*[https://jira.whamcloud.com/browse/LU-11605 LU-11605]: create_count stuck in 0 after changeing max_create_count to 0 and back 20 000
*[https://jira.whamcloud.com/browse/LU-11617 LU-11617]: lockdep exposed a possible deadlock in chlg_open()
*[https://jira.whamcloud.com/browse/LU-11620 LU-11620]: BUG: sleeping function called from invalid context at mm/slub.c:940
*[https://jira.whamcloud.com/browse/LU-11625 LU-11625]: ls -l returns &amp;quot;ls: cannot access Invalid argument&amp;quot;
*[https://jira.whamcloud.com/browse/LU-11626 LU-11626]: mdc: obd might go away while referenced by code in mdc_changelog
*[https://jira.whamcloud.com/browse/LU-11634 LU-11634]: sanityn/test_77 improvements
*[https://jira.whamcloud.com/browse/LU-11636 LU-11636]: t-f test_mkdir() does not support interop with non DNEII servers
*[https://jira.whamcloud.com/browse/LU-11647 LU-11647]: niobuf.c:330:ptlrpc_register_bulk()) ASSERTION( desc-&amp;gt;bd_md_count == 0 ) failed:
*[https://jira.whamcloud.com/browse/LU-11658 LU-11658]: The cl_cache may be uninitialized while osc is activating
*[https://jira.whamcloud.com/browse/LU-11661 LU-11661]: sanityn: test_47g failed
*[https://jira.whamcloud.com/browse/LU-11665 LU-11665]: sanity test 101c: FAIL: Small 4k read IO 240 !
*[https://jira.whamcloud.com/browse/LU-11669 LU-11669]: add project in yml_test_group()
*[https://jira.whamcloud.com/browse/LU-11670 LU-11670]: Incorrect size when using lockahead
*[https://jira.whamcloud.com/browse/LU-11672 LU-11672]: improving lru_max_age policy when lru resize is disabled
*[https://jira.whamcloud.com/browse/LU-11675 LU-11675]: Don't allow new HSM requests during CDT_INIT
*[https://jira.whamcloud.com/browse/LU-11678 LU-11678]: sanity-quota test 1 fails with 'user write success, but expect EDQUOT'
*[https://jira.whamcloud.com/browse/LU-11681 LU-11681]: sanity test 65i fails with 'find /mnt/lustre failed'
*[https://jira.whamcloud.com/browse/LU-11690 LU-11690]: LBUG with very wide striping: lod_ea_store_resize()) ASSERTION( round &amp;lt;= lov_mds_md_size(2000, (0x0BD30000 | 0x0BD0))
*[https://jira.whamcloud.com/browse/LU-11691 LU-11691]: lfs getstripe buffer overflows with very large stripe counts
*[https://jira.whamcloud.com/browse/LU-11696 LU-11696]: &amp;quot;lfs getsom&amp;quot; returns &amp;quot;24&amp;quot; (sizeof lustre_som_attr) to userspace
*[https://jira.whamcloud.com/browse/LU-11699 LU-11699]: lod_device_free()) ASSERTION( atomic_read(&amp;amp;lu-&amp;gt;ld_ref) == 0 ) failed: lu is ffff881a7e690000
*[https://jira.whamcloud.com/browse/LU-11700 LU-11700]: GPF in osp_reserved_mb_low_seq_write
*[https://jira.whamcloud.com/browse/LU-11701 LU-11701]: replay-single test_80a: FAIL: remote creation failed
*[https://jira.whamcloud.com/browse/LU-11702 LU-11702]: ibc_rxs is created and freed with different size
*[https://jira.whamcloud.com/browse/LU-11712 LU-11712]: Lustre build fails when CONFIG_BLK_DEV_INTEGRITY is unset
*[https://jira.whamcloud.com/browse/LU-11716 LU-11716]: sanity-scrub test_1b test: BUG: unable to handle kernel NULL pointer dereference IP: [&amp;lt;ffffffff816b68a9&amp;gt;] _raw_read_lock+0x9/0x20
*[https://jira.whamcloud.com/browse/LU-11719 LU-11719]: Refactor search_itree
*[https://jira.whamcloud.com/browse/LU-11720 LU-11720]: SRPM unnecessarily tied to kernel version
*[https://jira.whamcloud.com/browse/LU-11721 LU-11721]: &amp;quot;lfs df -i&amp;quot; prints used blocks percentage instead of inodes
*[https://jira.whamcloud.com/browse/LU-11723 LU-11723]: kernel update [RHEL7.6 3.10.0-957.1.3.el7]
*[https://jira.whamcloud.com/browse/LU-11729 LU-11729]: ARM: sanity test_810: BAD WRITE CHECKSUM with adler
*[https://jira.whamcloud.com/browse/LU-11737 LU-11737]: LustreError: 11060:0:(osd_handler.c:3985:osd_xattr_set()) ASSERTION( handle ) failed:
*[https://jira.whamcloud.com/browse/LU-11742 LU-11742]: ERROR: RPATH is not allowed
*[https://jira.whamcloud.com/browse/LU-11743 LU-11743]: lctl pool operations cannot be run on separate MGS system
*[https://jira.whamcloud.com/browse/LU-11749 LU-11749]: sanity-sec test 23b fails with 'Should return gid=60010 or 60010 on client2'
*[https://jira.whamcloud.com/browse/LU-11750 LU-11750]: lsvcgssd crash with latest krb5-libs
*[https://jira.whamcloud.com/browse/LU-11752 LU-11752]: sanity test 271f fails with '1 READ RPC occured'
*[https://jira.whamcloud.com/browse/LU-11755 LU-11755]: Remove redundant LASSERT() in ns_is_{client,server}()
*[https://jira.whamcloud.com/browse/LU-11756 LU-11756]: kib_conn leak
*[https://jira.whamcloud.com/browse/LU-11757 LU-11757]: lfs mkdir: Cannot allocate memory
*[https://jira.whamcloud.com/browse/LU-11758 LU-11758]: remove assertion from osp_statfs()
*[https://jira.whamcloud.com/browse/LU-11759 LU-11759]: racer cleanup
*[https://jira.whamcloud.com/browse/LU-11760 LU-11760]: formatted OST recognition change
*[https://jira.whamcloud.com/browse/LU-11761 LU-11761]: blocked MDT mount and high cpu usage from lodXXXX_recYYYY threads
*[https://jira.whamcloud.com/browse/LU-11765 LU-11765]: during failover test run, mdtest job fails, numerous stat failures 'No such file or directory'
*[https://jira.whamcloud.com/browse/LU-11768 LU-11768]: sanity-quota test 6 fails with ‘LNet: Service thread pid &amp;lt;pid&amp;gt; was inactive for …’
*[https://jira.whamcloud.com/browse/LU-11770 LU-11770]: preserve kernel API when T10-PI patches are applied
*[https://jira.whamcloud.com/browse/LU-11771 LU-11771]: bad output in target_handle_reconnect: Recovery already passed deadline 71578:57
*[https://jira.whamcloud.com/browse/LU-11773 LU-11773]: setstripe YAML API does not support lcme_flags
*[https://jira.whamcloud.com/browse/LU-11777 LU-11777]: interop: sanityn test 102 fails with 'check_fhandle_syscalls failed'
*[https://jira.whamcloud.com/browse/LU-11778 LU-11778]: interop: sanity test 317 fails with 'Expected Block 4096 got 10240 for f317.sanity'
*[https://jira.whamcloud.com/browse/LU-11779 LU-11779]: interop: sanity-hsm test 255 fails with 'request on 0x200007935:0x268:0x0 is not SUCCEED on mds1'
*[https://jira.whamcloud.com/browse/LU-11780 LU-11780]: interop: replay-single test 132a fails with ''Component #1 instantiation was not replayed''
*[https://jira.whamcloud.com/browse/LU-11790 LU-11790]: ext4: include terminating u32 in size of xattr entries when expanding inodes
*[https://jira.whamcloud.com/browse/LU-11796 LU-11796]: Remove LASSERT(r0-&amp;gt;lo_nr &amp;lt;= lov_targets_nr(dev)) in maintenance branches
*[https://jira.whamcloud.com/browse/LU-11798 LU-11798]: cur_grant goes to 0 and never increases with 2.8 client and 2.10 server
*[https://jira.whamcloud.com/browse/LU-11816 LU-11816]: LNet Health: Correct timeout defaults
*[https://jira.whamcloud.com/browse/LU-11821 LU-11821]: sizeof() needs correct casting to compare with negatives
*[https://jira.whamcloud.com/browse/LU-11825 LU-11825]: Remove LU-8964/pio feature &amp;amp; supporting framework
*[https://jira.whamcloud.com/browse/LU-11827 LU-11827]: Race between llog_cat_declare_add_rec and llog_cat_current_log
*[https://jira.whamcloud.com/browse/LU-11828 LU-11828]: PFL crashes when invariant checking is enabled
*[https://jira.whamcloud.com/browse/LU-11835 LU-11835]: DOM open resend doesn't return size
*[https://jira.whamcloud.com/browse/LU-11836 LU-11836]: DOM read-open resend vs getattr deadlock
*[https://jira.whamcloud.com/browse/LU-11849 LU-11849]: lfs find ! --projid doesn't work as expected
*[https://jira.whamcloud.com/browse/LU-11851 LU-11851]: kernel BUG at ...ldiskfs/htree_lock.c:665
*[https://jira.whamcloud.com/browse/LU-11855 LU-11855]: fix out-of-block vars
*[https://jira.whamcloud.com/browse/LU-11860 LU-11860]: lnetctl fails when configuring numeric addresses
*[https://jira.whamcloud.com/browse/LU-11861 LU-11861]: master can't build with lock debug enabled
*[https://jira.whamcloud.com/browse/LU-11862 LU-11862]: lfsck avoid unexpected repairing
*[https://jira.whamcloud.com/browse/LU-11867 LU-11867]: OST precreate object FID in LMA mismatch causes OST unusable
*[https://jira.whamcloud.com/browse/LU-11868 LU-11868]: ZFS ea size limited to 32K
*[https://jira.whamcloud.com/browse/LU-11871 LU-11871]: Missing man page lctl-nodemap-set-fileset
*[https://jira.whamcloud.com/browse/LU-11873 LU-11873]: sanity test_801a: FAIL: (2) unexpected barrier status 'expired'
*[https://jira.whamcloud.com/browse/LU-11878 LU-11878]: sanity test 103b: OOM because of too many bash processes: page allocation stalls for 18420ms
*[https://jira.whamcloud.com/browse/LU-11880 LU-11880]: Allow Lustre build on Raspbian and other Debian derivatives
*[https://jira.whamcloud.com/browse/LU-11881 LU-11881]: lctl pool_list: Value too large for defined data type (75)
*[https://jira.whamcloud.com/browse/LU-11883 LU-11883]: Make deny_unknown visible on default nodemap
*[https://jira.whamcloud.com/browse/LU-11891 LU-11891]: make --mdt-index usage consistent
*[https://jira.whamcloud.com/browse/LU-11892 LU-11892]: Memory leak in MDT Coordinator
*[https://jira.whamcloud.com/browse/LU-11894 LU-11894]: Check for asymmetrical route messages in LNet
*[https://jira.whamcloud.com/browse/LU-11897 LU-11897]: ineffective memory allocation in ptlrpc
*[https://jira.whamcloud.com/browse/LU-11898 LU-11898]: libcfs module parameter libcfs_debug_mb has no effect
*[https://jira.whamcloud.com/browse/LU-11899 LU-11899]: Possible resource/memory leaks
*[https://jira.whamcloud.com/browse/LU-11905 LU-11905]: Mismatched ENTRY/RETURN in mdc_intent_open_pack
*[https://jira.whamcloud.com/browse/LU-11907 LU-11907]: sanity fails to cleanup d60g.sanity
*[https://jira.whamcloud.com/browse/LU-11911 LU-11911]: lov_iocontrol: BUG: unable to handle kernel NULL pointer dereference at 0000000000000100
*[https://jira.whamcloud.com/browse/LU-11917 LU-11917]: sanity test_258a: error, failed to take i_mutex, rc=0
*[https://jira.whamcloud.com/browse/LU-11919 LU-11919]: cl_max_dirty_pages not zeroed on startup
*[https://jira.whamcloud.com/browse/LU-11920 LU-11920]: memory leak in lod_lds_buf_get()
*[https://jira.whamcloud.com/browse/LU-11922 LU-11922]: mkfs.lustre in 1.44.3.wc1 causes corruption if 'metadata_csum' option enabled
*[https://jira.whamcloud.com/browse/LU-11925 LU-11925]: Attributes not updated after open+append and write to archived,released file
*[https://jira.whamcloud.com/browse/LU-11926 LU-11926]: Lost lease lock on migrate error
*[https://jira.whamcloud.com/browse/LU-11927 LU-11927]: support for SLES12 SP4
*[https://jira.whamcloud.com/browse/LU-11930 LU-11930]: sbi_flags printing broke
*[https://jira.whamcloud.com/browse/LU-11931 LU-11931]: RDMA packets sent from client to MGS are timing out
*[https://jira.whamcloud.com/browse/LU-11933 LU-11933]: sanity-hsm: test_406 sanity: test_230b osd_declare_dir_delete() ASSERTION( dt_object_exists(dt) )
*[https://jira.whamcloud.com/browse/LU-11934 LU-11934]: replay-single test_70c: Oom on client
*[https://jira.whamcloud.com/browse/LU-11943 LU-11943]: many input/output error after soak running for couple of hours
*[https://jira.whamcloud.com/browse/LU-11944 LU-11944]: WARNING: at ../fs/attr.c:212 notify_change doing tiny_writes
*[https://jira.whamcloud.com/browse/LU-11946 LU-11946]: configure --enable-dist fails if libyaml-devel or zlib-devel are not installed
*[https://jira.whamcloud.com/browse/LU-11947 LU-11947]: Regression caused by LU-11461
*[https://jira.whamcloud.com/browse/LU-11951 LU-11951]: sanity: test_231a failure, idle disconnect &amp;amp; import generation disagreement
*[https://jira.whamcloud.com/browse/LU-11956 LU-11956]: conf-sanity test_32a failed with 1
*[https://jira.whamcloud.com/browse/LU-11960 LU-11960]: Add missing libssl-dev DEB package
*[https://jira.whamcloud.com/browse/LU-11964 LU-11964]: Heavy load and soft lockups on MDS with DOM
*[https://jira.whamcloud.com/browse/LU-11965 LU-11965]: interop: sanity test 311 fails with 'create_count is zero'
*[https://jira.whamcloud.com/browse/LU-11967 LU-11967]: MDS LBUG ASSERTION( o-&amp;gt;opo_reserved == 0 ) failed
*[https://jira.whamcloud.com/browse/LU-11975 LU-11975]: sanity test 60a hangs in llog_test_10
*[https://jira.whamcloud.com/browse/LU-11997 LU-11997]: Crash in lustre_swab_fiemap
*[https://jira.whamcloud.com/browse/LU-12013 LU-12013]: Crashes in sanity-lfsck test 13
*[https://jira.whamcloud.com/browse/LU-12014 LU-12014]: check correct size in ll_dom_finish_open()
*[https://jira.whamcloud.com/browse/LU-12017 LU-12017]: Truncate vs setxattr deadlock with DoM
*[https://jira.whamcloud.com/browse/LU-12018 LU-12018]: deadlock on OSS: quota reintegration vs memory release
*[https://jira.whamcloud.com/browse/LU-12020 LU-12020]: LustreError: 32657:0:(mdc_lib.c:137:mdc_pack_name()) ASSERTION( lu_name_is_valid_2(buf, cpy_len) ) failed:
*[https://jira.whamcloud.com/browse/LU-12021 LU-12021]: Error message of mdt_attr_valid_xlate() when 2.12 client to 2.10 server
*[https://jira.whamcloud.com/browse/LU-12025 LU-12025]: Adding OST may cause EIO - delay activation of new OSTs on existing filesystem
*[https://jira.whamcloud.com/browse/LU-12030 LU-12030]: rhel7.6 removed kmalloc-128 slab
*[https://jira.whamcloud.com/browse/LU-12034 LU-12034]: env allocation in ptlrpc_set_wait() causes slowdown on the client
*[https://jira.whamcloud.com/browse/LU-12037 LU-12037]: Possible DNE issue leading to hung filesystem
*[https://jira.whamcloud.com/browse/LU-12039 LU-12039]: Fix 'lfs mkdir' in sanity-selinux
*[https://jira.whamcloud.com/browse/LU-12040 LU-12040]: File lost during recovery
*[https://jira.whamcloud.com/browse/LU-12042 LU-12042]: sanity test_103a: FAIL: LU-974 umask test failed under remote dir
*[https://jira.whamcloud.com/browse/LU-12053 LU-12053]: intermittent ping failures with MR/DD
*[https://jira.whamcloud.com/browse/LU-12055 LU-12055]: lod: ignore root layout if parent's one includes pool
*[https://jira.whamcloud.com/browse/LU-12059 LU-12059]: Update ZFS Version to 0.7.13
*[https://jira.whamcloud.com/browse/LU-12065 LU-12065]: Client got evicted when lock callback timer expired on OSS
*[https://jira.whamcloud.com/browse/LU-12068 LU-12068]: sanity-lfsck test_6b: (7.2) 0x0 is not larger than 0x0
*[https://jira.whamcloud.com/browse/LU-12069 LU-12069]: fix styling in mdt_reint_migrate_internal()
*[https://jira.whamcloud.com/browse/LU-12072 LU-12072]: Simplify the code for lov operating
*[https://jira.whamcloud.com/browse/LU-12075 LU-12075]: mdt_reint_migrate_internal() can break CoS logic
*[https://jira.whamcloud.com/browse/LU-12080 LU-12080]: LNet Health: references left on eq
*[https://jira.whamcloud.com/browse/LU-12081 LU-12081]: rename shouldn't PDO lock target parent if it's remote
*[https://jira.whamcloud.com/browse/LU-12094 LU-12094]: NULL pointer dereference in lprocfs_import_seq_write
*[https://jira.whamcloud.com/browse/LU-12095 LU-12095]: ocd_connect_flags are wrong during reconnect
*[https://jira.whamcloud.com/browse/LU-12098 LU-12098]: changelog_deregister appears not to reliably clear all changelog entries
*[https://jira.whamcloud.com/browse/LU-12101 LU-12101]: lctl push causes a crash
*[https://jira.whamcloud.com/browse/LU-12104 LU-12104]: SEGV during &amp;quot;lfs find [--mdt-count=[+,-]&amp;lt;count&amp;gt;, --mdt-hash=&amp;lt;hashtype&amp;gt;]&amp;quot;
*[https://jira.whamcloud.com/browse/LU-12120 LU-12120]: LustreError: 15069:0:(tgt_grant.c:561:tgt_grant_incoming()) LBUG
*[https://jira.whamcloud.com/browse/LU-12127 LU-12127]: Improve LFSCK orphan handling
*[https://jira.whamcloud.com/browse/LU-12131 LU-12131]: Improve GSS/SSK handling in Lustre test suite
*[https://jira.whamcloud.com/browse/LU-12138 LU-12138]: kernel update [SLES12 SP4 4.12.14-95.13.1]
*[https://jira.whamcloud.com/browse/LU-12139 LU-12139]: kernel update [SLES12 SP3 4.4.176-94.88.1]
*[https://jira.whamcloud.com/browse/LU-12140 LU-12140]: DOM: limitaion of data size
*[https://jira.whamcloud.com/browse/LU-12141 LU-12141]: Wrong requires kernel version detected of lustre kmod built against target rhel7.6
*[https://jira.whamcloud.com/browse/LU-12147 LU-12147]: statone utility doesn't form correct string with gcc8
*[https://jira.whamcloud.com/browse/LU-12151 LU-12151]: metadata performance difference on root and non-root user
*[https://jira.whamcloud.com/browse/LU-12152 LU-12152]: lnetctl export corrupts memory on routers
*[https://jira.whamcloud.com/browse/LU-12160 LU-12160]: use-after-free in osd_object_delete()
*[https://jira.whamcloud.com/browse/LU-12165 LU-12165]: Enable quota enforcement crashed kernel
*[https://jira.whamcloud.com/browse/LU-12166 LU-12166]: Tests if ZFS backend project supported is broken
*[https://jira.whamcloud.com/browse/LU-12168 LU-12168]: obdfilter-survey SHORT msg
*[https://jira.whamcloud.com/browse/LU-12169 LU-12169]: Assertion on mdc_pack_name
*[https://jira.whamcloud.com/browse/LU-12172 LU-12172]: kernel update [RHEL7.6 3.10.0-957.10.1.el7]
*[https://jira.whamcloud.com/browse/LU-12178 LU-12178]: MDS deadlock with 2.12.0 (quotas?)
*[https://jira.whamcloud.com/browse/LU-12195 LU-12195]: sanity/43 and sanityn/14 fail on local setups
*[https://jira.whamcloud.com/browse/LU-12199 LU-12199]: md's are not detached from uncommitted messages that have health check performed on them
*[https://jira.whamcloud.com/browse/LU-12203 LU-12203]: sanity-lfsck test_36[b,c] defect: tests are to be skipped for FILESET
*[https://jira.whamcloud.com/browse/LU-12206 LU-12206]: error handling on mdt_init0()
*[https://jira.whamcloud.com/browse/LU-12208 LU-12208]: formatall() defect: LU-8323 breaks interop with mixed old clients installed
*[https://jira.whamcloud.com/browse/LU-12212 LU-12212]: Often requests timeouts during dbench run
*[https://jira.whamcloud.com/browse/LU-12218 LU-12218]: ASSERTION( mbits == (req-&amp;gt;rq_mbits &amp;amp; PTLRPC_BULK_OPS_MASK) ) failes if OBD_CONNECT_BULK_MBITS isn't used.
*[https://jira.whamcloud.com/browse/LU-12219 LU-12219]: obdfilter-survey: line 509: size * 1024 / (actual_rsz * thr): division by 0 (error token is &amp;quot;)&amp;quot;)
*[https://jira.whamcloud.com/browse/LU-12221 LU-12221]: LBUG: (statahead.c:477:ll_sai_put()) ASSERTION( !sa_has_callback(sai) )
*[https://jira.whamcloud.com/browse/LU-12225 LU-12225]: jobid_get_from_cache stalled on spin_lock(&amp;amp;pidmap-&amp;gt;jp_lock)
*[https://jira.whamcloud.com/browse/LU-12227 LU-12227]: Lustre init script does not check if ZFS devices are already mounted
*[https://jira.whamcloud.com/browse/LU-12229 LU-12229]: ost-pools test 1j fails with 'test_1j returned 1'
*[https://jira.whamcloud.com/browse/LU-12242 LU-12242]: kernel update [RHEL7.6 3.10.0-957.12.1.el7]
*[https://jira.whamcloud.com/browse/LU-12247 LU-12247]: sanityn test 34 fails with 'test_34 returned 1'
*[https://jira.whamcloud.com/browse/LU-12248 LU-12248]: sanity test_418: df and lfs df inodes output mismatch
*[https://jira.whamcloud.com/browse/LU-12253 LU-12253]: lfs: double free or corruption (!prev)
*[https://jira.whamcloud.com/browse/LU-12261 LU-12261]: sanity test 43b fails with 'expected error, got success'
*[https://jira.whamcloud.com/browse/LU-12263 LU-12263]: build breakage with 2.12.53 tag
*[https://jira.whamcloud.com/browse/LU-12264 LU-12264]: The lnet peer discovery queue (lnet_peer.lp_dc_pendq) is susceptible to concurrent manipulation
*[https://jira.whamcloud.com/browse/LU-12266 LU-12266]: Fix up non-directory creation in SGID directories
*[https://jira.whamcloud.com/browse/LU-12267 LU-12267]: sanity test_103a: some ACL tests fail with SELinux enforced
*[https://jira.whamcloud.com/browse/LU-12276 LU-12276]: Lustre client compilation failing on CentOS 7.6 + MOFED 4.6
*[https://jira.whamcloud.com/browse/LU-12279 LU-12279]: client got evicted due to network issue.
*[https://jira.whamcloud.com/browse/LU-12282 LU-12282]: Pass IB_OPTIONS to debian rules doesn't work
*[https://jira.whamcloud.com/browse/LU-12296 LU-12296]: ll_dom_lock_cancel() should zero kms attribute
*[https://jira.whamcloud.com/browse/LU-12299 LU-12299]: avoid panic for too large cpu partitions
*[https://jira.whamcloud.com/browse/LU-12306 LU-12306]: kernel update [RHEL7.6 3.10.0-957.12.2.el7]
*[https://jira.whamcloud.com/browse/LU-12309 LU-12309]: write fails with -EOPNOTSUPP with zfs 0.8.0-rc5 using 0.7.x pool
*[https://jira.whamcloud.com/browse/LU-12314 LU-12314]: Add Missing Description to sanity test 258a
*[https://jira.whamcloud.com/browse/LU-12323 LU-12323]: save_stack_trace_tsk is not exported on arm architectures
*[https://jira.whamcloud.com/browse/LU-12324 LU-12324]: zero transno on transaction commit
*[https://jira.whamcloud.com/browse/LU-12328 LU-12328]: FLR mirroring on 2.12.1-1 not usable if OST is down
*[https://jira.whamcloud.com/browse/LU-12335 LU-12335]: mb_prealloc_table table read/write code is racy
*[https://jira.whamcloud.com/browse/LU-12342 LU-12342]: lsvcgss config file overwritten on update
*[https://jira.whamcloud.com/browse/LU-12343 LU-12343]: osc_lock.c:687:osc_ldlm_weigh_ast()) LBUG
*[https://jira.whamcloud.com/browse/LU-12345 LU-12345]: backport - ext4: optimize ext4_find_delalloc_range() in nodelalloc mode
*[https://jira.whamcloud.com/browse/LU-12350 LU-12350]: sanity-flr test_33: file content error: expected: ost1, actual: ost2
*[https://jira.whamcloud.com/browse/LU-12352 LU-12352]: libcfs crashes with certain cpu_npartitions values
*[https://jira.whamcloud.com/browse/LU-12361 LU-12361]: cp --sparse doesn't work correctly in
*[https://jira.whamcloud.com/browse/LU-12367 LU-12367]: readahead page count calculation is incorrect for unaligned reads
*[https://jira.whamcloud.com/browse/LU-12374 LU-12374]: client went down w/ panic during lustre_rmmod
*[https://jira.whamcloud.com/browse/LU-12375 LU-12375]: lnet should start after opa service
*[https://jira.whamcloud.com/browse/LU-12381 LU-12381]: o2iblnd uses wrong IB interface
*[https://jira.whamcloud.com/browse/LU-12382 LU-12382]: Deadloop on tiny write
*[https://jira.whamcloud.com/browse/LU-12383 LU-12383]: lfs project inhert difference between ldiskfs and zfs
*[https://jira.whamcloud.com/browse/LU-12385 LU-12385]: 2.12.2: IOR read testing reliably inducing LNetError: Timed out RDMA with ...@o2ib1 (6): c: 0, oc: 0, rc: 63
*[https://jira.whamcloud.com/browse/LU-12387 LU-12387]: l_tunedisk does not properly handle multipath devices
*[https://jira.whamcloud.com/browse/LU-12392 LU-12392]: gcc8 can't build lfs.c
*[https://jira.whamcloud.com/browse/LU-12394 LU-12394]: lctl get_param llite.lfs*.extents_stats only displays first two buckets
*[https://jira.whamcloud.com/browse/LU-12395 LU-12395]: Failed dependencies while installing lustre-client-tests and lustre-iokit rpms on RHEL 8.0 client
*[https://jira.whamcloud.com/browse/LU-12396 LU-12396]: lfs df output is treated as binary data on RHEL 8.0 client
*[https://jira.whamcloud.com/browse/LU-12399 LU-12399]: sanity test_420: FAIL: incorrect perms on /mnt/lustre/d420.sanity/testdir/testfile
*[https://jira.whamcloud.com/browse/LU-12401 LU-12401]: Various issues with checksum calculation for Kerberos and SSK
*[https://jira.whamcloud.com/browse/LU-12402 LU-12402]: LNet Health: lnet_finalize() recurssion
*[https://jira.whamcloud.com/browse/LU-12411 LU-12411]: Hang on lnetctl route del
*[https://jira.whamcloud.com/browse/LU-12412 LU-12412]: mdt: task umount:19248 blocked for more than 120 seconds
*[https://jira.whamcloud.com/browse/LU-12420 LU-12420]: llog_reader crashes when reading llog that is not inited
*[https://jira.whamcloud.com/browse/LU-12422 LU-12422]: LNet MR routing: update route state in case discovery is off
*[https://jira.whamcloud.com/browse/LU-12423 LU-12423]: LNet MR routing: only push updates if discovery is enabled
*[https://jira.whamcloud.com/browse/LU-12424 LU-12424]: LNet MR routing: possible loop when discovery is off
*[https://jira.whamcloud.com/browse/LU-12427 LU-12427]: LNet MR routing: output a warning if discovery is off
*[https://jira.whamcloud.com/browse/LU-12428 LU-12428]: sanity-sec: test_13 nodemap_del failed with 1
*[https://jira.whamcloud.com/browse/LU-12431 LU-12431]: Close race on cp_state changes
*[https://jira.whamcloud.com/browse/LU-12436 LU-12436]: Memory allocation failure error dropped
*[https://jira.whamcloud.com/browse/LU-12438 LU-12438]: Use kernel_read/write instead of vfs_read/write for PCC
*[https://jira.whamcloud.com/browse/LU-12441 LU-12441]: Response tracker is not detached on router ping reply
*[https://jira.whamcloud.com/browse/LU-12443 LU-12443]: sanity test_271f: @@@@@@ FAIL: expect 1 READ RPC, occured
*[https://jira.whamcloud.com/browse/LU-12446 LU-12446]: Variable STRIPE_BYTES Undefined under sanityn.sh/16b
*[https://jira.whamcloud.com/browse/LU-12447 LU-12447]: Fedora28 Lustre client build failure
*[https://jira.whamcloud.com/browse/LU-12455 LU-12455]: readcache max file size show/store inconsistent
*[https://jira.whamcloud.com/browse/LU-12456 LU-12456]: kernel update [RHEL8.0 4.18.0-80.4.2.el8_0]
*[https://jira.whamcloud.com/browse/LU-12457 LU-12457]: support for RHEL 7.7
*[https://jira.whamcloud.com/browse/LU-12458 LU-12458]: kernel update [RHEL7.6 3.10.0-957.21.3.el7]
*[https://jira.whamcloud.com/browse/LU-12462 LU-12462]: osc_cache_writeback_range(): ASSERTION( ext-&amp;gt;oe_start &amp;gt;= start &amp;amp;&amp;amp; ext-&amp;gt;oe_end &amp;lt;= end ) failed
*[https://jira.whamcloud.com/browse/LU-12472 LU-12472]: Kerberos: sanity-krb5.sh needs some fixes
*[https://jira.whamcloud.com/browse/LU-12473 LU-12473]: pool_list by path incorrectly prints path as pool prefix
*[https://jira.whamcloud.com/browse/LU-12474 LU-12474]: racer can't be found on Ubuntu 18.04
*[https://jira.whamcloud.com/browse/LU-12478 LU-12478]: RHEL8 packaging
*[https://jira.whamcloud.com/browse/LU-12479 LU-12479]: gcc8 warnings
*[https://jira.whamcloud.com/browse/LU-12481 LU-12481]: conf-sanity test_61: setfattr: /mnt/lustre/f61.conf-sanity: Argument list too long
*[https://jira.whamcloud.com/browse/LU-12482 LU-12482]: sanity-hsm uses nonexisting variable
*[https://jira.whamcloud.com/browse/LU-12483 LU-12483]: sanity test 60h improper mds version check.
*[https://jira.whamcloud.com/browse/LU-12484 LU-12484]: typo in is_project_quota_supported for zfs case
*[https://jira.whamcloud.com/browse/LU-12485 LU-12485]: (osd_handler.c:2146:osd_object_release()) ASSERTION( !(o-&amp;gt;oo_destroyed == 0 &amp;amp;&amp;amp; o-&amp;gt;oo_inode &amp;amp;&amp;amp; o-&amp;gt;oo_inode-&amp;gt;i_nlink == 0) ) faile
*[https://jira.whamcloud.com/browse/LU-12489 LU-12489]: Tests marked slow that are not slow (anymore?)
*[https://jira.whamcloud.com/browse/LU-12491 LU-12491]: large-scale: crash in lu_env_remove() RIP: memcmp+0x9/0x50
*[https://jira.whamcloud.com/browse/LU-12494 LU-12494]: kernel update [SLES12 SP4 4.12.14-95.19.1]
*[https://jira.whamcloud.com/browse/LU-12495 LU-12495]: sanity test_413b: subdirs shouldn't be evenly distributed
*[https://jira.whamcloud.com/browse/LU-12501 LU-12501]: lfs df can never return
*[https://jira.whamcloud.com/browse/LU-12510 LU-12510]: mds server hangs cv_wait_common
*[https://jira.whamcloud.com/browse/LU-12513 LU-12513]: Address YAML limitations
*[https://jira.whamcloud.com/browse/LU-12523 LU-12523]: Add jobid to rpctrace debug messages
*[https://jira.whamcloud.com/browse/LU-12524 LU-12524]: mdc_close() matched open debug msg causes memory fragmentation
*[https://jira.whamcloud.com/browse/LU-12536 LU-12536]: Processes stuck in unkillable sleep waiting on IO during Lustre re-export of NFS testing
*[https://jira.whamcloud.com/browse/LU-12537 LU-12537]: recovery-mds-scale failover_mds: BUG: unable to handle kernel NULL pointer dereference at (null) IP: lnet_attach_rsp_tracker.isra.32+0xad/0x200 [lnet]
*[https://jira.whamcloud.com/browse/LU-12538 LU-12538]: bad spinlock magic in sanity test 413b
*[https://jira.whamcloud.com/browse/LU-12539 LU-12539]: Pass --with-o2ib option along when building deb packages
*[https://jira.whamcloud.com/browse/LU-12540 LU-12540]: overstripe landing broke a MKFS options handling
*[https://jira.whamcloud.com/browse/LU-12558 LU-12558]: kernel update [SLES12 SP3 4.4.180-94.100.1]
*[https://jira.whamcloud.com/browse/LU-12559 LU-12559]: Reconnecting from idle exposes import in IMP_NEW state, resulting in EIO
*[https://jira.whamcloud.com/browse/LU-12560 LU-12560]: acceptance small doesn't use full path for finding test-groups
*[https://jira.whamcloud.com/browse/LU-12565 LU-12565]: Use bit locking in obd_echo
*[https://jira.whamcloud.com/browse/LU-12566 LU-12566]: GPF when umounting client
*[https://jira.whamcloud.com/browse/LU-12568 LU-12568]: LNetError: 28086:0:(lib-move.c:2862:lnet_detach_rsp_tracker()) ASSERTION( rspt-&amp;gt;rspt_cpt == cpt ) failed
*[https://jira.whamcloud.com/browse/LU-12569 LU-12569]: IBLND_CREDITS_HIGHWATER does not check connection queue depth
*[https://jira.whamcloud.com/browse/LU-12570 LU-12570]: sanity test 134a crash with SSK in use
*[https://jira.whamcloud.com/browse/LU-12575 LU-12575]: lbuild: build MOFED on el8
*[https://jira.whamcloud.com/browse/LU-12579 LU-12579]: runtests: test_1: @@@@@@ FAIL: Space not all freed: now 309264kB, was 307632kB.
*[https://jira.whamcloud.com/browse/LU-12581 LU-12581]: Slab object &amp;quot;Freechain corrupt&amp;quot; on client
*[https://jira.whamcloud.com/browse/LU-12586 LU-12586]: truncate to start of uninstantiated PFL component silently fails
*[https://jira.whamcloud.com/browse/LU-12587 LU-12587]: DIO fallback to Buffer IO unexpectedly
*[https://jira.whamcloud.com/browse/LU-12589 LU-12589]: sanity test_102a: setfattr: /mnt/lustre/f102a.sanity: Numerical result out of range
*[https://jira.whamcloud.com/browse/LU-12590 LU-12590]: Lustre lustre_msg_hdr_size_v2() bug
*[https://jira.whamcloud.com/browse/LU-12593 LU-12593]: update_log corruption
*[https://jira.whamcloud.com/browse/LU-12595 LU-12595]: Attempt to add route using non-local gateway should return EHOSTUNREACH, not EINVAL
*[https://jira.whamcloud.com/browse/LU-12600 LU-12600]: Lustre tgt_brw_write() bug
*[https://jira.whamcloud.com/browse/LU-12602 LU-12602]: Lustre mdt_getxattr_pack_reply() bug
*[https://jira.whamcloud.com/browse/LU-12603 LU-12603]: Lustre ldlm_request_cancel() bug
*[https://jira.whamcloud.com/browse/LU-12604 LU-12604]: Lustre mdt_file_secctx_unpack() bug
*[https://jira.whamcloud.com/browse/LU-12605 LU-12605]: Lustre target_handle_connect() bug
*[https://jira.whamcloud.com/browse/LU-12608 LU-12608]: kernel update [RHEL7.6 3.10.0-957.27.2.el7]
*[https://jira.whamcloud.com/browse/LU-12611 LU-12611]: LNet Routing: don't stop adding routes for any error
*[https://jira.whamcloud.com/browse/LU-12612 LU-12612]: Lustre osd_bufs_get() bug
*[https://jira.whamcloud.com/browse/LU-12613 LU-12613]: Lustre lustre_msg_string() bug
*[https://jira.whamcloud.com/browse/LU-12614 LU-12614]: Lustre ldlm_cancel_hpreq_check() bug
*[https://jira.whamcloud.com/browse/LU-12615 LU-12615]: Lustre mdt_object_remote() bug
*[https://jira.whamcloud.com/browse/LU-12616 LU-12616]: MDS node crashed LustreError: 23042:0:(mdt_handler.c:5135:mdt_init0()) ASSERTION( info != ((void *)0) )
*[https://jira.whamcloud.com/browse/LU-12622 LU-12622]: Another batch of test fixes for SSK
*[https://jira.whamcloud.com/browse/LU-12625 LU-12625]: sometimes configure can't detect timespec64 with gcc8
*[https://jira.whamcloud.com/browse/LU-12626 LU-12626]: Attempt to create existing net returns EINVAL
*[https://jira.whamcloud.com/browse/LU-12627 LU-12627]: ASSERTION( info-&amp;gt;fti_attr.la_valid == 0 )
*[https://jira.whamcloud.com/browse/LU-12639 LU-12639]: sanity test 317 uses uninitialized variable $facet
*[https://jira.whamcloud.com/browse/LU-12650 LU-12650]: get_root_path() filesystem name compare error that leads to fid2path fail
*[https://jira.whamcloud.com/browse/LU-12657 LU-12657]: sanity/103 and sanityn/25 fail with 4.18 kernel
*[https://jira.whamcloud.com/browse/LU-12660 LU-12660]: kernel update [SLES12 SP4 4.12.14-95.29.1]
*[https://jira.whamcloud.com/browse/LU-12671 LU-12671]: replay-vbr accesses non-existent mdd.sync_permission setting
*[https://jira.whamcloud.com/browse/LU-12672 LU-12672]: recovery-small test 66 does not work correctly
*[https://jira.whamcloud.com/browse/LU-12674 LU-12674]: osp should handle -EINPROGRESS on llog objects
*[https://jira.whamcloud.com/browse/LU-12675 LU-12675]: LBUG &amp;quot;(lu_object.c:1196:lu_device_fini()) ASSERTION( atomic_read(&amp;amp;d-&amp;gt;ld_ref) == 0 ) failed: Refcount is 1&amp;quot; running sanity.sh on latest master
*[https://jira.whamcloud.com/browse/LU-12681 LU-12681]: Data corruption - due incorrect KMS with SEL files
*[https://jira.whamcloud.com/browse/LU-12685 LU-12685]: ll_statahead_threda has incorrect error handling code
*[https://jira.whamcloud.com/browse/LU-12686 LU-12686]: ln_mt_waitq use by lnet monitor thread is completely ineffective
*[https://jira.whamcloud.com/browse/LU-12690 LU-12690]: error handling of ll_och_fill()
*[https://jira.whamcloud.com/browse/LU-12691 LU-12691]: obd_max_recoverable_clients is not atomic
*[https://jira.whamcloud.com/browse/LU-12694 LU-12694]: make &amp;quot;lfs quota&amp;quot; display correct group quota information
*[https://jira.whamcloud.com/browse/LU-12703 LU-12703]: sanity test_421a: FAIL: rmfid with fsname failed
*[https://jira.whamcloud.com/browse/LU-12705 LU-12705]: build fails on power9 client
*[https://jira.whamcloud.com/browse/LU-12707 LU-12707]: mds-survey test 1 crashes with a NULL pointer dereference in echo_object_free()
*[https://jira.whamcloud.com/browse/LU-12712 LU-12712]: sanity-pfl tests triggering “not SEL magic on SEL file”
*[https://jira.whamcloud.com/browse/LU-12719 LU-12719]: crash in lustre_find_lwp_by_index()
*[https://jira.whamcloud.com/browse/LU-12724 LU-12724]: kernel update [RHEL7.7 3.10.0-1062.1.1.el7]
*[https://jira.whamcloud.com/browse/LU-12739 LU-12739]: Race with discovery thread completion and message queueing
*[https://jira.whamcloud.com/browse/LU-12745 LU-12745]: Lustre fails to compile against zfs dkms 0.8+
*[https://jira.whamcloud.com/browse/LU-12751 LU-12751]: error() is missing in few places in sanity.sh
*[https://jira.whamcloud.com/browse/LU-12753 LU-12753]: sanity test_300a: FAIL: 1:stripe_count is 1, expect 2
*[https://jira.whamcloud.com/browse/LU-12755 LU-12755]: CPU soft lockup on mkfs.lustre
*[https://jira.whamcloud.com/browse/LU-12758 LU-12758]: sanity-quota test 65 fails with 'usr quota not match'
*[https://jira.whamcloud.com/browse/LU-12760 LU-12760]: sanity test_161d incorrect use of stack_trap
*[https://jira.whamcloud.com/browse/LU-12763 LU-12763]: Use alternate ping processing for non-mr peers
*[https://jira.whamcloud.com/browse/LU-12764 LU-12764]: ubuntu16 client build failure
*[https://jira.whamcloud.com/browse/LU-12769 LU-12769]: replay-dual test 0b hangs in client mount
*[https://jira.whamcloud.com/browse/LU-12773 LU-12773]: sanity test 805 uses do_node instead of do_facet
*[https://jira.whamcloud.com/browse/LU-12777 LU-12777]: conf-sanity test 103 fails with ‘set mdt quota type failed’
*[https://jira.whamcloud.com/browse/LU-12783 LU-12783]: interop: sanity test 27I fails with “multiop failed”
*[https://jira.whamcloud.com/browse/LU-12784 LU-12784]: interop: sanity test 102ha fails with “saving trusted.big on /mnt/lustre/f102ha.sanity failed”
*[https://jira.whamcloud.com/browse/LU-12790 LU-12790]: LustreError: 96800:0:(jobid.c:103:jobid_get_from_environ()) jobid: get 'PBS_JOBID' failed: rc = -75
*[https://jira.whamcloud.com/browse/LU-12795 LU-12795]: lp_utils is duplicated and not used.
*[https://jira.whamcloud.com/browse/LU-12799 LU-12799]: NULL pointer dereference IP: ptlrpc_disconnect_and_idle_import
*[https://jira.whamcloud.com/browse/LU-12800 LU-12800]: mdd_is_parent() goes into infinite loop
*[https://jira.whamcloud.com/browse/LU-12803 LU-12803]: lustre in staging interferes with 2.12.2 on Ubuntu 18.04
*[https://jira.whamcloud.com/browse/LU-12824 LU-12824]: Unable to add single Infiniband interface to multiple o2ib LNets
*[https://jira.whamcloud.com/browse/LU-12838 LU-12838]: ptlrpc watchdog ratelimiting is broken
*[https://jira.whamcloud.com/browse/LU-12842 LU-12842]: lctl llog_print doesn't accept snapshot names with leading number
*[https://jira.whamcloud.com/browse/LU-12844 LU-12844]: error: ‘strncpy’ specified bound depends on the length of the source argument
*[https://jira.whamcloud.com/browse/LU-12859 LU-12859]: Both &amp;quot;flock&amp;quot; and &amp;quot;localflock&amp;quot; appear in /proc/mounts
*[https://jira.whamcloud.com/browse/LU-12893 LU-12893]: lnet: peer ni selection broken
*[https://jira.whamcloud.com/browse/LU-12903 LU-12903]: lctl-pcc man page does not exist
*[https://jira.whamcloud.com/browse/LU-12932 LU-12932]: parallel-scale test rr_alloc fails with ‘failed while setting qos_threshold_rr &amp;amp; creat_count’
*[https://jira.whamcloud.com/browse/LU-12946 LU-12946]: Multipath path flapping issue
*[https://jira.whamcloud.com/browse/LU-13023 LU-13023]: PCC: The size of the PCC copy is not truncated to 0 when attach
*[https://jira.whamcloud.com/browse/LU-13030 LU-13030]: pcc: auto_attach doesn't work after client cache cleared

''' Task '''
*[https://jira.whamcloud.com/browse/LU-10171 LU-10171]: define pct(a,b) once
*[https://jira.whamcloud.com/browse/LU-11394 LU-11394]: Updates for ZFS 0.8.0, no separate SPL
*[https://jira.whamcloud.com/browse/LU-11683 LU-11683]: Update ZFS Version to 0.7.12
*[https://jira.whamcloud.com/browse/LU-11689 LU-11689]: lfs project should proceed all dirs if hit errors
*[https://jira.whamcloud.com/browse/LU-12026 LU-12026]: verify that MDS stores atime/mtime/ctime during LSOM update
*[https://jira.whamcloud.com/browse/LU-12561 LU-12561]: Remove RHEL6/SLES11 support from master for 2.13

''' Technical task '''
*[https://jira.whamcloud.com/browse/LU-10777 LU-10777]: DoM performance is bad with FIO write
*[https://jira.whamcloud.com/browse/LU-10894 LU-10894]: Compilebench results are lower than expected
*[https://jira.whamcloud.com/browse/LU-11298 LU-11298]: LNet: Router peer instead of Router Peer NI
*[https://jira.whamcloud.com/browse/LU-11299 LU-11299]: LNet: Router pinger
*[https://jira.whamcloud.com/browse/LU-11300 LU-11300]: LNet: Router Aliveness and Health
*[https://jira.whamcloud.com/browse/LU-11378 LU-11378]: LNet: modify router selection to be MR aware
*[https://jira.whamcloud.com/browse/LU-11421 LU-11421]: DoM: manual migration OST-MDT, MDT-MDT
*[https://jira.whamcloud.com/browse/LU-11470 LU-11470]: LNet Health: Add drop all rule
*[https://jira.whamcloud.com/browse/LU-11475 LU-11475]: LNet discovery: allow deleting primary_nid in router case
*[https://jira.whamcloud.com/browse/LU-11477 LU-11477]: handle health for both incoming and outgoing messages
*[https://jira.whamcloud.com/browse/LU-11478 LU-11478]: LNet: discovery sequence numbers could be misleading
*[https://jira.whamcloud.com/browse/LU-11551 LU-11551]: LNet: Do not allow deletion fo rouer interface
*[https://jira.whamcloud.com/browse/LU-11641 LU-11641]: LNet Router: handle discovery off case
*[https://jira.whamcloud.com/browse/LU-11649 LU-11649]: lnet router: handle health off
*[https://jira.whamcloud.com/browse/LU-11664 LU-11664]: LNet Router: push updates when router interfaces change
*[https://jira.whamcloud.com/browse/LU-12074 LU-12074]: Update lustre tests
*[https://jira.whamcloud.com/browse/LU-12163 LU-12163]: Fix cpt confusion
*[https://jira.whamcloud.com/browse/LU-12164 LU-12164]: LNet: code cleanup
*[https://jira.whamcloud.com/browse/LU-12200 LU-12200]: LNet: MR Routing use peer_timeout
*[https://jira.whamcloud.com/browse/LU-12201 LU-12201]: LNet: detach response tracker
*[https://jira.whamcloud.com/browse/LU-12237 LU-12237]: LNet Health: Initialize recovery ping mdh
*[https://jira.whamcloud.com/browse/LU-12249 LU-12249]: LNet Health: list corruption
*[https://jira.whamcloud.com/browse/LU-12254 LU-12254]: lnet: correct discovery event queue release
*[https://jira.whamcloud.com/browse/LU-12339 LU-12339]: LNet Health: selecting loopback interface for sending
*[https://jira.whamcloud.com/browse/LU-12344 LU-12344]: LNet Health: tweak health errors
*[https://jira.whamcloud.com/browse/LU-12526 LU-12526]: Auto attach for PCC during IO

''' Question/Request '''
*[https://jira.whamcloud.com/browse/LU-9581 LU-9581]: recovery-small tests 52 60 remove from ALWAYS_EXCEPT
*[https://jira.whamcloud.com/browse/LU-12298 LU-12298]: Cannot Start Lustre 2.12.1 Server

[[Category:Releases]]</ns1:text>
      <ns1:sha1>l208nxqejsy0ggdorjjcezf5bnlt0dt</ns1:sha1>
    </ns1:revision>
  </ns1:page>
</mediawiki>