<?xml version='1.0' encoding='utf-8'?>
<mediawiki xmlns:ns1="http://www.mediawiki.org/xml/export-0.11/" xmlns:xsi="http://www.w3.org/2001/XMLSchema-instance" xsi:schemaLocation="http://www.mediawiki.org/xml/export-0.11/ http://www.mediawiki.org/xml/export-0.11.xsd" version="0.11" xml:lang="en">
  <ns1:siteinfo>
    <ns1:sitename>Lustre Wiki</ns1:sitename>
    <ns1:dbname>wiki_lustre_org</ns1:dbname>
    <ns1:base>http://wiki.lustre.org/Main_Page</ns1:base>
    <ns1:generator>MediaWiki 1.39.7</ns1:generator>
    <ns1:case>first-letter</ns1:case>
    <ns1:namespaces>
      <ns1:namespace key="-2" case="first-letter">Media</ns1:namespace>
      <ns1:namespace key="-1" case="first-letter">Special</ns1:namespace>
      <ns1:namespace key="0" case="first-letter" />
      <ns1:namespace key="1" case="first-letter">Talk</ns1:namespace>
      <ns1:namespace key="2" case="first-letter">User</ns1:namespace>
      <ns1:namespace key="3" case="first-letter">User talk</ns1:namespace>
      <ns1:namespace key="4" case="first-letter">Lustre Wiki</ns1:namespace>
      <ns1:namespace key="5" case="first-letter">Lustre Wiki talk</ns1:namespace>
      <ns1:namespace key="6" case="first-letter">File</ns1:namespace>
      <ns1:namespace key="7" case="first-letter">File talk</ns1:namespace>
      <ns1:namespace key="8" case="first-letter">MediaWiki</ns1:namespace>
      <ns1:namespace key="9" case="first-letter">MediaWiki talk</ns1:namespace>
      <ns1:namespace key="10" case="first-letter">Template</ns1:namespace>
      <ns1:namespace key="11" case="first-letter">Template talk</ns1:namespace>
      <ns1:namespace key="12" case="first-letter">Help</ns1:namespace>
      <ns1:namespace key="13" case="first-letter">Help talk</ns1:namespace>
      <ns1:namespace key="14" case="first-letter">Category</ns1:namespace>
      <ns1:namespace key="15" case="first-letter">Category talk</ns1:namespace>
    </ns1:namespaces>
  </ns1:siteinfo>
  <ns1:page>
    <ns1:title>Lustre Debugging for Developers</ns1:title>
    <ns1:ns>0</ns1:ns>
    <ns1:id>826</ns1:id>
    <ns1:revision>
      <ns1:id>2251</ns1:id>
      <ns1:parentid>1848</ns1:parentid>
      <ns1:timestamp>2017-03-09T08:20:15Z</ns1:timestamp>
      <ns1:contributor>
        <ns1:username>Hdoreau</ns1:username>
        <ns1:id>33</ns1:id>
      </ns1:contributor>
      <ns1:comment>/* Finding memory leaks using leak_finder.pl */</ns1:comment>
      <ns1:origin>2251</ns1:origin>
      <ns1:model>wikitext</ns1:model>
      <ns1:format>text/x-wiki</ns1:format>
      <ns1:text bytes="2656" sha1="desvm7hctwqp8vsovw62q2vv6yj0qwq" xml:space="preserve">{| class='wikitable'
|- 
!Note: This page originated on the old Lustre wiki. It was identified as likely having value and was migrated to the new wiki. It is in the process of being reviewed/updated and may currently have content that is out of date.
|}

&lt;small&gt;''(Updated: Jan 2011)''&lt;/small&gt;
__TOC__
The procedures below may be useful to developers debugging Lustre code.

== Adding Debugging to the Source Code ==
The debug infrastructure provides a number of macros that can be used in Lustre™ source code to aid in debugging or reporting serious errors. 

To use these macros, you will need to set the ''DEBUG_SUBSYSTEM'' variable at the top of the file to as shown below:

 #define DEBUG_SUBSYSTEM S_PORTALS

A list of available macros with descriptions is provided in see [http://wiki.lustre.org/manual/LustreManual20_HTML/LustreDebugging.html#50438274_pgfId-1296027 Section 28.3.1: ''Adding Debugging to the Lustre Source Code''] in the [http://wiki.lustre.org/manual/LustreManual20_HTML/index.html ''Lustre Operations Manual''].

== Accessing a ''ptlrpc'' Request History ==
Each service maintains a request history, which can be useful for first occurrence troubleshooting. ''Prlrpc'' is an RPC protocol layered on LNET. This protocol deals with stateful servers and has semantics and built in support for recovery. ''Prlrpc'' is a subsystem in the Lustre Debug Messages section.

For more information about how to use ''prlrpc'', see [http://wiki.lustre.org/manual/LustreManual20_HTML/LustreDebugging.html#50438274_pgfId-1296100 Section 28.3.2: ''Accessing a Ptlrpc Request History''] in the [http://wiki.lustre.org/manual/LustreManual20_HTML/index.html ''Lustre Operations Manual''].

=Finding memory leaks using ''leak_finder.pl''=

Memory leaks can occur in code when memory has been allocated and then not freed once it is no longer required. The ''leak_finder.pl'' program provides a way to find memory leaks.  

For details, see [http://doc.lustre.org/lustre_manual.xhtml#idm139902791322240 Section 31.3.3: ''Finding Memory Leaks Using leak_finder.pl''] in the [http://doc.lustre.org/lustre_manual.xhtml ''Lustre Operations Manual''].

=Using LWT Tracing=
Lustre offers a lightweight tracing facility called LWT. It prints fixed size requests into a buffer and is much faster than LDEBUG. The LWT tracking facility can be used to debug difficult problems. Use of LWT tracing requires rebuilding LNET code.

Dumped LWT trace-based records contain:
* Current CPU
* Process counter
* Pointer to file
* Pointer to line in the file
* Four void * pointers 

An ''lctl'' command can be used to dump the logs to files.

[[Category: NeedsReview]]</ns1:text>
      <ns1:sha1>desvm7hctwqp8vsovw62q2vv6yj0qwq</ns1:sha1>
    </ns1:revision>
  </ns1:page>
</mediawiki>