<?xml version='1.0' encoding='utf-8'?>
<mediawiki xmlns:ns1="http://www.mediawiki.org/xml/export-0.11/" xmlns:xsi="http://www.w3.org/2001/XMLSchema-instance" xsi:schemaLocation="http://www.mediawiki.org/xml/export-0.11/ http://www.mediawiki.org/xml/export-0.11.xsd" version="0.11" xml:lang="en">
  <ns1:siteinfo>
    <ns1:sitename>Lustre Wiki</ns1:sitename>
    <ns1:dbname>wiki_lustre_org</ns1:dbname>
    <ns1:base>http://wiki.lustre.org/Main_Page</ns1:base>
    <ns1:generator>MediaWiki 1.39.7</ns1:generator>
    <ns1:case>first-letter</ns1:case>
    <ns1:namespaces>
      <ns1:namespace key="-2" case="first-letter">Media</ns1:namespace>
      <ns1:namespace key="-1" case="first-letter">Special</ns1:namespace>
      <ns1:namespace key="0" case="first-letter" />
      <ns1:namespace key="1" case="first-letter">Talk</ns1:namespace>
      <ns1:namespace key="2" case="first-letter">User</ns1:namespace>
      <ns1:namespace key="3" case="first-letter">User talk</ns1:namespace>
      <ns1:namespace key="4" case="first-letter">Lustre Wiki</ns1:namespace>
      <ns1:namespace key="5" case="first-letter">Lustre Wiki talk</ns1:namespace>
      <ns1:namespace key="6" case="first-letter">File</ns1:namespace>
      <ns1:namespace key="7" case="first-letter">File talk</ns1:namespace>
      <ns1:namespace key="8" case="first-letter">MediaWiki</ns1:namespace>
      <ns1:namespace key="9" case="first-letter">MediaWiki talk</ns1:namespace>
      <ns1:namespace key="10" case="first-letter">Template</ns1:namespace>
      <ns1:namespace key="11" case="first-letter">Template talk</ns1:namespace>
      <ns1:namespace key="12" case="first-letter">Help</ns1:namespace>
      <ns1:namespace key="13" case="first-letter">Help talk</ns1:namespace>
      <ns1:namespace key="14" case="first-letter">Category</ns1:namespace>
      <ns1:namespace key="15" case="first-letter">Category talk</ns1:namespace>
    </ns1:namespaces>
  </ns1:siteinfo>
  <ns1:page>
    <ns1:title>Multi-Rail LNet</ns1:title>
    <ns1:ns>0</ns1:ns>
    <ns1:id>368</ns1:id>
    <ns1:revision>
      <ns1:id>1932</ns1:id>
      <ns1:parentid>1474</ns1:parentid>
      <ns1:timestamp>2016-09-13T08:45:55Z</ns1:timestamp>
      <ns1:contributor>
        <ns1:username>OlafWeber</ns1:username>
        <ns1:id>38</ns1:id>
      </ns1:contributor>
      <ns1:comment>Add links to the videos from LUG and OFA.</ns1:comment>
      <ns1:origin>1932</ns1:origin>
      <ns1:model>wikitext</ns1:model>
      <ns1:format>text/x-wiki</ns1:format>
      <ns1:text bytes="2234" sha1="hdfh5d4zhv7slkphd5xt32o5x1txuze" xml:space="preserve">This is a placeholder page for information on the Multi-Rail LNet project.

== Goal ==

The goal of the Multi-Rail LNet project is to extend LNet to support nodes using multiple interfaces to communicate with each other. These interfaces can be on the same LNet network, or on different LNet networks.

This [[Multi-Rail_LNet/LAD15_Lustre_Interface_Bonding|presentation]] given by [[User:OlafWeber|Olaf Weber]] at the Lustre Developer Summit 2015 at [http://www.eofs.eu/?id=lad15 LAD'15] is an introduction to the ideas underlying the project.

There is a description of the [[Media:Multi-Rail+Scope+and+Requirements+Document.pdf|scope and requirements]] of the project, as agreed between Intel and SGI.

Working from there we've created a [[Media:Multi-Rail_High-Level_Design_20150119.pdf|high level design]] document. This document actually consists of two parts: the first half gives a high-level overview of the chosen approach, while the second half contains more detailed design notes for the various parts involved. Since no design survives a confrontation with implementation intact, we intend to update the design document to match the implementation as it evolves. Ultimately we want to turn this into a set of wiki pages that document how the final code works, but this takes too much time to be feasible for the intermediate versions.

In April, Olaf Weber did a presentation on the topic at LUG 2016. InsideHPC posted the [http://insidehpc.com/2016/07/multirail-lustre/ video]. Amir Shehata gave a presentation on the same subject at the 2016 openfabrics workshop. RichReport's youtube channel has the [https://www.youtube.com/watch?v=cKuhveClfok video].

== Documents ==

Placeholder section for the public documents for the project.

* Presentation slides used at the Lustre Developer Summit 2015 [[Media:LAD15_Lustre_Interface_Bonding_Final.pdf|Lustre Interface Bonding (1MB PDF)]]. Also check this [[Multi-Rail_LNet/LAD15_Lustre_Interface_Bonding|summary]] of the presentation.
* [[Media:Multi-Rail+Scope+and+Requirements+Document.pdf|Multi-Rail Scope and Requirements Document (2.7MB PDF)]]
* [[Media:Multi-Rail_High-Level_Design_20150119.pdf|Multi-Rail High Level Design Document (1.13 MB PDF)]]

[[Category: LNET]]</ns1:text>
      <ns1:sha1>hdfh5d4zhv7slkphd5xt32o5x1txuze</ns1:sha1>
    </ns1:revision>
  </ns1:page>
</mediawiki>