<?xml version='1.0' encoding='utf-8'?>
<mediawiki xmlns:ns1="http://www.mediawiki.org/xml/export-0.11/" xmlns:xsi="http://www.w3.org/2001/XMLSchema-instance" xsi:schemaLocation="http://www.mediawiki.org/xml/export-0.11/ http://www.mediawiki.org/xml/export-0.11.xsd" version="0.11" xml:lang="en">
  <ns1:siteinfo>
    <ns1:sitename>Lustre Wiki</ns1:sitename>
    <ns1:dbname>wiki_lustre_org</ns1:dbname>
    <ns1:base>http://wiki.lustre.org/Main_Page</ns1:base>
    <ns1:generator>MediaWiki 1.39.7</ns1:generator>
    <ns1:case>first-letter</ns1:case>
    <ns1:namespaces>
      <ns1:namespace key="-2" case="first-letter">Media</ns1:namespace>
      <ns1:namespace key="-1" case="first-letter">Special</ns1:namespace>
      <ns1:namespace key="0" case="first-letter" />
      <ns1:namespace key="1" case="first-letter">Talk</ns1:namespace>
      <ns1:namespace key="2" case="first-letter">User</ns1:namespace>
      <ns1:namespace key="3" case="first-letter">User talk</ns1:namespace>
      <ns1:namespace key="4" case="first-letter">Lustre Wiki</ns1:namespace>
      <ns1:namespace key="5" case="first-letter">Lustre Wiki talk</ns1:namespace>
      <ns1:namespace key="6" case="first-letter">File</ns1:namespace>
      <ns1:namespace key="7" case="first-letter">File talk</ns1:namespace>
      <ns1:namespace key="8" case="first-letter">MediaWiki</ns1:namespace>
      <ns1:namespace key="9" case="first-letter">MediaWiki talk</ns1:namespace>
      <ns1:namespace key="10" case="first-letter">Template</ns1:namespace>
      <ns1:namespace key="11" case="first-letter">Template talk</ns1:namespace>
      <ns1:namespace key="12" case="first-letter">Help</ns1:namespace>
      <ns1:namespace key="13" case="first-letter">Help talk</ns1:namespace>
      <ns1:namespace key="14" case="first-letter">Category</ns1:namespace>
      <ns1:namespace key="15" case="first-letter">Category talk</ns1:namespace>
    </ns1:namespaces>
  </ns1:siteinfo>
  <ns1:page>
    <ns1:title>Reporting Bugs</ns1:title>
    <ns1:ns>0</ns1:ns>
    <ns1:id>893</ns1:id>
    <ns1:revision>
      <ns1:id>3995</ns1:id>
      <ns1:parentid>1955</ns1:parentid>
      <ns1:timestamp>2021-05-11T19:48:28Z</ns1:timestamp>
      <ns1:contributor>
        <ns1:username>Adilger</ns1:username>
        <ns1:id>8</ns1:id>
      </ns1:contributor>
      <ns1:comment>link to Jira instead of Bugzilla</ns1:comment>
      <ns1:origin>3995</ns1:origin>
      <ns1:model>wikitext</ns1:model>
      <ns1:format>text/x-wiki</ns1:format>
      <ns1:text bytes="2444" sha1="2pn8klwi98gub5cs10fsde9k8msyasc" xml:space="preserve">&lt;small&gt;''(Updated: May 2021)''&lt;/small&gt;
__TOC__
[https://jira.whamcloud.com Jira] for Lustre™ is an issue tracker as well as a bug tracker. It is a one-stop repository for:
* Bugs
* Enhancement requests
* Tracking patch submission
* Issue dependency tracking

A bug-tracking system is less-error prone and superior to email in dozens of ways. For this reason we ask that all the above issues be handled exclusively through Jira.

All of the important links described below are accessible from the Jira main page or the toolbar at the bottom of each Bugzilla page.

== Opening an Account ==
To use Jira, you will need to open an account. On the Main page are instructions for creating a new account.  This is, unfortunately, no longer a totally automated process due to spam and malicious users.

== Searching for Bugs ==

You can search for bugs in Jira in two ways: 

* Enter the issue number (e.g. [https://jira.whamcloud.com/browse/LU-12000 LU-12000]) or [https://jira.whamcloud.com/issues/?jql= search on a keyword].
* Search for specific text or specify detailed or complex criteria with the [https://jira.whamcloud.com/issues/?jql= Advanced Search] option.

== Filing a Bug ==
To file a bug, complete these steps:

1. Before opening a new bug report, do a quick search to avoid filing a duplicate bug.

2. To enter a new bug report, click on "Create" in the top menu. 

3. In the bug report form, fill in as many fields as you can. If your version of Lustre isn't listed, include it in a note in the bug Environment.

4. Include a useful Summary line and a more complete Description. At a minimum, include the following:

* Describe the problem that you're solving, the feature that you're adding, or the enhancement that you're requesting.
* If you are reporting a bug, describe precisely the behavior that you're seeing and the behavior that you think is correct.
* Provide a minimal a test case. For example, if 'tar' is crashing, try to narrow the issue down to a specific ''syscall'' with e.g. ''strace''. If you have tried to narrow it down without success, tell us what you tried.
* If you are submitting a patch, see [[Submitting Changes]] for a detailed procedure.

== Priority Bugs ==
If you have a support contract for Lustre, contact your support provider directly.

'''''Note:''''' Severity 1 bugs can be filed only for corruption events or by customers with support contracts who are experiencing a production outage event.</ns1:text>
      <ns1:sha1>2pn8klwi98gub5cs10fsde9k8msyasc</ns1:sha1>
    </ns1:revision>
  </ns1:page>
</mediawiki>